[
  {
    "char": "ت",
    "start": 2.765,
    "end": 4.429,
    "idx": 0
  },
  {
    "char": "ب",
    "start": 4.429,
    "end": 5.149,
    "idx": 1
  },
  {
    "char": "ت",
    "start": 5.149,
    "end": 6.221,
    "idx": 2
  },
  {
    "char": "ي",
    "start": 6.221,
    "end": 6.461,
    "idx": 3
  },
  {
    "char": "د",
    "start": 6.461,
    "end": 6.861000000000001,
    "idx": 4
  },
  {
    "char": "ا",
    "start": 6.861000000000001,
    "end": 7.471,
    "idx": 5
  },
  {
    "char": "أ",
    "start": 7.551,
    "end": 7.8870000000000005,
    "idx": 6
  },
  {
    "char": "ب",
    "start": 7.8870000000000005,
    "end": 8.287,
    "idx": 7
  },
  {
    "char": "ي",
    "start": 8.287,
    "end": 8.732,
    "idx": 8
  },
  {
    "char": "ل",
    "start": 8.812,
    "end": 9.244,
    "idx": 9
  },
  {
    "char": "غ",
    "start": 9.244,
    "end": 9.676,
    "idx": 10
  },
  {
    "char": "ب",
    "start": 9.676,
    "end": 11.212,
    "idx": 11
  },
  {
    "char": "و",
    "start": 11.212,
    "end": 12.155999999999999,
    "idx": 12
  },
  {
    "char": "ت",
    "start": 12.155999999999999,
    "end": 16.875999999999998,
    "idx": 13
  },
  {
    "char": "ب",
    "start": 16.875999999999998,
    "end": 17.212,
    "idx": 14
  },
  {
    "char": "م",
    "start": 17.212,
    "end": 17.772,
    "idx": 15
  },
  {
    "char": "ا",
    "start": 17.772,
    "end": 18.204,
    "idx": 16
  },
  {
    "char": "أ",
    "start": 18.204,
    "end": 18.524,
    "idx": 17
  },
  {
    "char": "غ",
    "start": 18.524,
    "end": 19.212,
    "idx": 18
  },
  {
    "char": "ن",
    "start": 19.212,
    "end": 19.644,
    "idx": 19
  },
  {
    "char": "ى",
    "start": 19.644,
    "end": 19.915999999999997,
    "idx": 20
  },
  {
    "char": "ع",
    "start": 19.915999999999997,
    "end": 20.348,
    "idx": 21
  },
  {
    "char": "ن",
    "start": 20.348,
    "end": 20.732,
    "idx": 22
  },
  {
    "char": "ه",
    "start": 20.732,
    "end": 21.507,
    "idx": 23
  },
  {
    "char": "م",
    "start": 21.607,
    "end": 21.942999999999998,
    "idx": 24
  },
  {
    "char": "ا",
    "start": 21.942999999999998,
    "end": 22.279,
    "idx": 25
  },
  {
    "char": "ل",
    "start": 22.279,
    "end": 22.887,
    "idx": 26
  },
  {
    "char": "ه",
    "start": 22.887,
    "end": 23.65,
    "idx": 27
  },
  {
    "char": "و",
    "start": 23.73,
    "end": 24.13,
    "idx": 28
  },
  {
    "char": "م",
    "start": 24.13,
    "end": 24.434,
    "idx": 29
  },
  {
    "char": "ا",
    "start": 24.434,
    "end": 25.132,
    "idx": 30
  },
  {
    "char": "ك",
    "start": 25.192,
    "end": 25.4,
    "idx": 31
  },
  {
    "char": "س",
    "start": 25.4,
    "end": 25.64,
    "idx": 32
  },
  {
    "char": "ب",
    "start": 25.64,
    "end": 26.393,
    "idx": 33
  },
  {
    "char": "س",
    "start": 30.035,
    "end": 30.163,
    "idx": 34
  },
  {
    "char": "ي",
    "start": 30.163,
    "end": 30.659,
    "idx": 35
  },
  {
    "char": "ص",
    "start": 30.659,
    "end": 31.171,
    "idx": 36
  },
  {
    "char": "ل",
    "start": 31.171,
    "end": 31.523,
    "idx": 37
  },
  {
    "char": "ى",
    "start": 31.523,
    "end": 31.731,
    "idx": 38
  },
  {
    "char": "ن",
    "start": 31.731,
    "end": 31.923000000000002,
    "idx": 39
  },
  {
    "char": "ا",
    "start": 31.923000000000002,
    "end": 32.339,
    "idx": 40
  },
  {
    "char": "ر",
    "start": 32.339,
    "end": 32.595,
    "idx": 41
  },
  {
    "char": "ا",
    "start": 32.595,
    "end": 33.427,
    "idx": 42
  },
  {
    "char": "ذ",
    "start": 33.427,
    "end": 34.515,
    "idx": 43
  },
  {
    "char": "ا",
    "start": 34.515,
    "end": 34.803,
    "idx": 44
  },
  {
    "char": "ت",
    "start": 34.803,
    "end": 35.027,
    "idx": 45
  },
  {
    "char": "ل",
    "start": 35.027,
    "end": 35.619,
    "idx": 46
  },
  {
    "char": "ه",
    "start": 35.619,
    "end": 35.875,
    "idx": 47
  },
  {
    "char": "ب",
    "start": 35.875,
    "end": 36.243,
    "idx": 48
  },
  {
    "char": "و",
    "start": 36.243,
    "end": 37.891,
    "idx": 49
  },
  {
    "char": "م",
    "start": 37.891,
    "end": 40.483000000000004,
    "idx": 50
  },
  {
    "char": "ر",
    "start": 40.483000000000004,
    "end": 40.995000000000005,
    "idx": 51
  },
  {
    "char": "أ",
    "start": 40.995000000000005,
    "end": 41.347,
    "idx": 52
  },
  {
    "char": "ت",
    "start": 41.347,
    "end": 41.715,
    "idx": 53
  },
  {
    "char": "ه",
    "start": 41.715,
    "end": 42.848,
    "idx": 54
  },
  {
    "char": "ح",
    "start": 43.029,
    "end": 44.293000000000006,
    "idx": 55
  },
  {
    "char": "م",
    "start": 44.293000000000006,
    "end": 44.661,
    "idx": 56
  },
  {
    "char": "ا",
    "start": 44.661,
    "end": 44.821000000000005,
    "idx": 57
  },
  {
    "char": "ن",
    "start": 44.821000000000005,
    "end": 45.141000000000005,
    "idx": 58
  },
  {
    "char": "ة",
    "start": 45.141000000000005,
    "end": 45.525000000000006,
    "idx": 59
  },
  {
    "char": "ا",
    "start": 45.525000000000006,
    "end": 45.893,
    "idx": 60
  },
  {
    "char": "ل",
    "start": 45.893,
    "end": 46.229000000000006,
    "idx": 61
  },
  {
    "char": "ح",
    "start": 46.229000000000006,
    "end": 46.629000000000005,
    "idx": 62
  },
  {
    "char": "ط",
    "start": 46.629000000000005,
    "end": 47.157000000000004,
    "idx": 63
  },
  {
    "char": "ب",
    "start": 47.157000000000004,
    "end": 49.525000000000006,
    "idx": 64
  },
  {
    "char": "ف",
    "start": 49.525000000000006,
    "end": 49.909000000000006,
    "idx": 65
  },
  {
    "char": "ي",
    "start": 49.909000000000006,
    "end": 50.076,
    "idx": 66
  },
  {
    "char": "ج",
    "start": 50.256,
    "end": 50.656,
    "idx": 67
  },
  {
    "char": "ي",
    "start": 50.656,
    "end": 50.88,
    "idx": 68
  },
  {
    "char": "د",
    "start": 50.88,
    "end": 51.12,
    "idx": 69
  },
  {
    "char": "ه",
    "start": 51.12,
    "end": 51.792,
    "idx": 70
  },
  {
    "char": "ا",
    "start": 51.792,
    "end": 52.078,
    "idx": 71
  },
  {
    "char": "ح",
    "start": 52.238,
    "end": 52.43,
    "idx": 72
  },
  {
    "char": "ب",
    "start": 52.43,
    "end": 52.942,
    "idx": 73
  },
  {
    "char": "ل",
    "start": 52.942,
    "end": 53.339,
    "idx": 74
  },
  {
    "char": "م",
    "start": 54.24,
    "end": 54.368,
    "idx": 75
  },
  {
    "char": "ن",
    "start": 54.368,
    "end": 55.696000000000005,
    "idx": 76
  },
  {
    "char": "م",
    "start": 55.696000000000005,
    "end": 55.872,
    "idx": 77
  },
  {
    "char": "س",
    "start": 55.872,
    "end": 56.288000000000004,
    "idx": 78
  },
  {
    "char": "د",
    "start": 56.288000000000004,
    "end": 56.903,
    "idx": 79
  }
]