[
  {
    "char": "س",
    "start": 2.208,
    "end": 2.4160000000000004,
    "idx": 0
  },
  {
    "char": "أ",
    "start": 2.4160000000000004,
    "end": 2.608,
    "idx": 1
  },
  {
    "char": "ل",
    "start": 2.608,
    "end": 3.009,
    "idx": 2
  },
  {
    "char": "س",
    "start": 3.169,
    "end": 3.345,
    "idx": 3
  },
  {
    "char": "ا",
    "start": 3.345,
    "end": 3.841,
    "idx": 4
  },
  {
    "char": "ئ",
    "start": 3.841,
    "end": 4.017,
    "idx": 5
  },
  {
    "char": "ل",
    "start": 4.017,
    "end": 4.417,
    "idx": 6
  },
  {
    "char": "ب",
    "start": 4.417,
    "end": 4.577,
    "idx": 7
  },
  {
    "char": "ع",
    "start": 4.577,
    "end": 5.1370000000000005,
    "idx": 8
  },
  {
    "char": "ذ",
    "start": 5.1370000000000005,
    "end": 6.833,
    "idx": 9
  },
  {
    "char": "ا",
    "start": 6.833,
    "end": 7.425000000000001,
    "idx": 10
  },
  {
    "char": "ب",
    "start": 7.425000000000001,
    "end": 7.872999999999999,
    "idx": 11
  },
  {
    "char": "و",
    "start": 7.872999999999999,
    "end": 8.209,
    "idx": 12
  },
  {
    "char": "ا",
    "start": 8.209,
    "end": 9.201,
    "idx": 13
  },
  {
    "char": "ق",
    "start": 9.201,
    "end": 9.969,
    "idx": 14
  },
  {
    "char": "ع",
    "start": 9.969,
    "end": 10.289,
    "idx": 15
  },
  {
    "char": "ل",
    "start": 10.289,
    "end": 10.465,
    "idx": 16
  },
  {
    "char": "ل",
    "start": 10.465,
    "end": 10.977,
    "idx": 17
  },
  {
    "char": "ك",
    "start": 10.977,
    "end": 14.513,
    "idx": 18
  },
  {
    "char": "ا",
    "start": 14.513,
    "end": 14.817,
    "idx": 19
  },
  {
    "char": "ف",
    "start": 14.817,
    "end": 15.585,
    "idx": 20
  },
  {
    "char": "ر",
    "start": 15.585,
    "end": 16.256999999999998,
    "idx": 21
  },
  {
    "char": "ي",
    "start": 16.256999999999998,
    "end": 16.544999999999998,
    "idx": 22
  },
  {
    "char": "ن",
    "start": 16.544999999999998,
    "end": 16.727,
    "idx": 23
  },
  {
    "char": "ل",
    "start": 16.827,
    "end": 17.147000000000002,
    "idx": 24
  },
  {
    "char": "ي",
    "start": 17.147000000000002,
    "end": 17.579,
    "idx": 25
  },
  {
    "char": "س",
    "start": 17.579,
    "end": 17.931,
    "idx": 26
  },
  {
    "char": "ل",
    "start": 17.931,
    "end": 18.491000000000003,
    "idx": 27
  },
  {
    "char": "ه",
    "start": 18.491000000000003,
    "end": 19.01,
    "idx": 28
  },
  {
    "char": "د",
    "start": 19.13,
    "end": 19.273999999999997,
    "idx": 29
  },
  {
    "char": "ا",
    "start": 19.273999999999997,
    "end": 19.497999999999998,
    "idx": 30
  },
  {
    "char": "ف",
    "start": 19.497999999999998,
    "end": 19.625999999999998,
    "idx": 31
  },
  {
    "char": "ع",
    "start": 19.625999999999998,
    "end": 20.233999999999998,
    "idx": 32
  },
  {
    "char": "م",
    "start": 20.233999999999998,
    "end": 22.154,
    "idx": 33
  },
  {
    "char": "ن",
    "start": 22.154,
    "end": 22.362,
    "idx": 34
  },
  {
    "char": "ا",
    "start": 22.362,
    "end": 23.322,
    "idx": 35
  },
  {
    "char": "ل",
    "start": 23.322,
    "end": 23.546,
    "idx": 36
  },
  {
    "char": "ل",
    "start": 23.546,
    "end": 24.041999999999998,
    "idx": 37
  },
  {
    "char": "ه",
    "start": 24.041999999999998,
    "end": 24.314,
    "idx": 38
  },
  {
    "char": "ذ",
    "start": 24.314,
    "end": 24.602,
    "idx": 39
  },
  {
    "char": "ي",
    "start": 24.602,
    "end": 24.937,
    "idx": 40
  },
  {
    "char": "ا",
    "start": 25.338,
    "end": 25.706,
    "idx": 41
  },
  {
    "char": "ل",
    "start": 25.706,
    "end": 25.85,
    "idx": 42
  },
  {
    "char": "م",
    "start": 25.85,
    "end": 25.962,
    "idx": 43
  },
  {
    "char": "ع",
    "start": 25.962,
    "end": 26.042,
    "idx": 44
  },
  {
    "char": "ا",
    "start": 26.042,
    "end": 26.138,
    "idx": 45
  },
  {
    "char": "ر",
    "start": 26.138,
    "end": 26.794,
    "idx": 46
  },
  {
    "char": "ج",
    "start": 26.794,
    "end": 27.22,
    "idx": 47
  },
  {
    "char": "ت",
    "start": 30.592,
    "end": 30.656,
    "idx": 48
  },
  {
    "char": "ع",
    "start": 30.656,
    "end": 30.72,
    "idx": 49
  },
  {
    "char": "ر",
    "start": 30.72,
    "end": 31.392,
    "idx": 50
  },
  {
    "char": "ج",
    "start": 31.392,
    "end": 31.613,
    "idx": 51
  },
  {
    "char": "ا",
    "start": 31.673,
    "end": 32.009,
    "idx": 52
  },
  {
    "char": "ل",
    "start": 32.009,
    "end": 32.217,
    "idx": 53
  },
  {
    "char": "م",
    "start": 32.217,
    "end": 32.376999999999995,
    "idx": 54
  },
  {
    "char": "ل",
    "start": 32.376999999999995,
    "end": 32.632999999999996,
    "idx": 55
  },
  {
    "char": "ا",
    "start": 32.632999999999996,
    "end": 33.272999999999996,
    "idx": 56
  },
  {
    "char": "ئ",
    "start": 33.272999999999996,
    "end": 33.369,
    "idx": 57
  },
  {
    "char": "ك",
    "start": 33.369,
    "end": 33.736999999999995,
    "idx": 58
  },
  {
    "char": "ة",
    "start": 33.736999999999995,
    "end": 33.977,
    "idx": 59
  },
  {
    "char": "و",
    "start": 33.977,
    "end": 34.265,
    "idx": 60
  },
  {
    "char": "ا",
    "start": 34.265,
    "end": 34.632999999999996,
    "idx": 61
  },
  {
    "char": "ل",
    "start": 34.632999999999996,
    "end": 35.097,
    "idx": 62
  },
  {
    "char": "ر",
    "start": 35.097,
    "end": 35.769,
    "idx": 63
  },
  {
    "char": "و",
    "start": 35.769,
    "end": 36.473,
    "idx": 64
  },
  {
    "char": "ح",
    "start": 36.473,
    "end": 36.94,
    "idx": 65
  },
  {
    "char": "إ",
    "start": 37.04,
    "end": 37.296,
    "idx": 66
  },
  {
    "char": "ل",
    "start": 37.296,
    "end": 37.472,
    "idx": 67
  },
  {
    "char": "ي",
    "start": 37.472,
    "end": 38.128,
    "idx": 68
  },
  {
    "char": "ه",
    "start": 38.128,
    "end": 38.422,
    "idx": 69
  },
  {
    "char": "ف",
    "start": 38.582,
    "end": 38.838,
    "idx": 70
  },
  {
    "char": "ي",
    "start": 38.838,
    "end": 39.334,
    "idx": 71
  },
  {
    "char": "ي",
    "start": 39.334,
    "end": 39.814,
    "idx": 72
  },
  {
    "char": "و",
    "start": 39.814,
    "end": 40.518,
    "idx": 73
  },
  {
    "char": "م",
    "start": 40.518,
    "end": 41.446,
    "idx": 74
  },
  {
    "char": "ك",
    "start": 41.666,
    "end": 42.034,
    "idx": 75
  },
  {
    "char": "ا",
    "start": 42.034,
    "end": 42.29,
    "idx": 76
  },
  {
    "char": "ن",
    "start": 42.29,
    "end": 42.748,
    "idx": 77
  },
  {
    "char": "م",
    "start": 42.908,
    "end": 43.052,
    "idx": 78
  },
  {
    "char": "ق",
    "start": 43.052,
    "end": 43.436,
    "idx": 79
  },
  {
    "char": "د",
    "start": 43.436,
    "end": 44.252,
    "idx": 80
  },
  {
    "char": "ا",
    "start": 44.252,
    "end": 44.412,
    "idx": 81
  },
  {
    "char": "ر",
    "start": 44.412,
    "end": 44.956,
    "idx": 82
  },
  {
    "char": "ه",
    "start": 44.956,
    "end": 45.611,
    "idx": 83
  },
  {
    "char": "خ",
    "start": 45.812,
    "end": 45.988,
    "idx": 84
  },
  {
    "char": "م",
    "start": 45.988,
    "end": 46.66,
    "idx": 85
  },
  {
    "char": "س",
    "start": 46.66,
    "end": 47.044,
    "idx": 86
  },
  {
    "char": "ي",
    "start": 47.044,
    "end": 47.428,
    "idx": 87
  },
  {
    "char": "ن",
    "start": 47.428,
    "end": 47.734,
    "idx": 88
  },
  {
    "char": "أ",
    "start": 47.834,
    "end": 48.138000000000005,
    "idx": 89
  },
  {
    "char": "ل",
    "start": 48.138000000000005,
    "end": 48.346000000000004,
    "idx": 90
  },
  {
    "char": "ف",
    "start": 48.346000000000004,
    "end": 48.730000000000004,
    "idx": 91
  },
  {
    "char": "س",
    "start": 48.730000000000004,
    "end": 48.954,
    "idx": 92
  },
  {
    "char": "ن",
    "start": 48.954,
    "end": 49.114000000000004,
    "idx": 93
  },
  {
    "char": "ة",
    "start": 49.114000000000004,
    "end": 49.514,
    "idx": 94
  },
  {
    "char": "ف",
    "start": 49.514,
    "end": 49.61000000000001,
    "idx": 95
  },
  {
    "char": "ا",
    "start": 49.61000000000001,
    "end": 53.274,
    "idx": 96
  },
  {
    "char": "ص",
    "start": 53.274,
    "end": 53.722,
    "idx": 97
  },
  {
    "char": "ب",
    "start": 53.722,
    "end": 53.834,
    "idx": 98
  },
  {
    "char": "ر",
    "start": 53.834,
    "end": 54.142,
    "idx": 99
  },
  {
    "char": "ص",
    "start": 54.282,
    "end": 54.346,
    "idx": 100
  },
  {
    "char": "ب",
    "start": 54.346,
    "end": 54.474,
    "idx": 101
  },
  {
    "char": "ر",
    "start": 54.474,
    "end": 54.937999999999995,
    "idx": 102
  },
  {
    "char": "اً",
    "start": 54.937999999999995,
    "end": 55.123,
    "idx": 103
  },
  {
    "char": "ج",
    "start": 56.525,
    "end": 56.829,
    "idx": 104
  },
  {
    "char": "م",
    "start": 56.829,
    "end": 57.485,
    "idx": 105
  },
  {
    "char": "ي",
    "start": 57.485,
    "end": 58.028999999999996,
    "idx": 106
  },
  {
    "char": "ل",
    "start": 58.028999999999996,
    "end": 58.269,
    "idx": 107
  },
  {
    "char": "اً",
    "start": 58.269,
    "end": 58.708,
    "idx": 108
  },
  {
    "char": "إ",
    "start": 63.008,
    "end": 63.152,
    "idx": 109
  },
  {
    "char": "ن",
    "start": 63.152,
    "end": 64.352,
    "idx": 110
  },
  {
    "char": "ه",
    "start": 64.352,
    "end": 64.8,
    "idx": 111
  },
  {
    "char": "م",
    "start": 64.8,
    "end": 65.232,
    "idx": 112
  },
  {
    "char": "ي",
    "start": 65.232,
    "end": 65.76,
    "idx": 113
  },
  {
    "char": "ر",
    "start": 65.76,
    "end": 66.48,
    "idx": 114
  },
  {
    "char": "و",
    "start": 66.48,
    "end": 66.64,
    "idx": 115
  },
  {
    "char": "ن",
    "start": 66.64,
    "end": 66.848,
    "idx": 116
  },
  {
    "char": "ه",
    "start": 66.848,
    "end": 67.535,
    "idx": 117
  },
  {
    "char": "ب",
    "start": 67.675,
    "end": 67.963,
    "idx": 118
  },
  {
    "char": "ع",
    "start": 67.963,
    "end": 68.651,
    "idx": 119
  },
  {
    "char": "ي",
    "start": 68.651,
    "end": 68.923,
    "idx": 120
  },
  {
    "char": "د",
    "start": 68.923,
    "end": 69.27499999999999,
    "idx": 121
  },
  {
    "char": "اً",
    "start": 69.27499999999999,
    "end": 72.651,
    "idx": 122
  },
  {
    "char": "و",
    "start": 72.651,
    "end": 73.115,
    "idx": 123
  },
  {
    "char": "ن",
    "start": 73.115,
    "end": 73.371,
    "idx": 124
  },
  {
    "char": "ر",
    "start": 73.371,
    "end": 73.86699999999999,
    "idx": 125
  },
  {
    "char": "ا",
    "start": 73.86699999999999,
    "end": 74.187,
    "idx": 126
  },
  {
    "char": "ه",
    "start": 74.187,
    "end": 74.485,
    "idx": 127
  },
  {
    "char": "ق",
    "start": 74.666,
    "end": 74.746,
    "idx": 128
  },
  {
    "char": "ر",
    "start": 74.746,
    "end": 75.562,
    "idx": 129
  },
  {
    "char": "ي",
    "start": 75.562,
    "end": 76.122,
    "idx": 130
  },
  {
    "char": "ب",
    "start": 76.122,
    "end": 76.378,
    "idx": 131
  },
  {
    "char": "اً",
    "start": 76.378,
    "end": 76.666,
    "idx": 132
  },
  {
    "char": "ي",
    "start": 76.666,
    "end": 80.98599999999999,
    "idx": 133
  },
  {
    "char": "و",
    "start": 80.98599999999999,
    "end": 81.402,
    "idx": 134
  },
  {
    "char": "م",
    "start": 81.402,
    "end": 81.556,
    "idx": 135
  },
  {
    "char": "ت",
    "start": 81.736,
    "end": 81.816,
    "idx": 136
  },
  {
    "char": "ك",
    "start": 81.816,
    "end": 82.072,
    "idx": 137
  },
  {
    "char": "و",
    "start": 82.072,
    "end": 82.632,
    "idx": 138
  },
  {
    "char": "ن",
    "start": 82.632,
    "end": 82.918,
    "idx": 139
  },
  {
    "char": "ا",
    "start": 82.998,
    "end": 83.51,
    "idx": 140
  },
  {
    "char": "ل",
    "start": 83.51,
    "end": 83.83,
    "idx": 141
  },
  {
    "char": "س",
    "start": 83.83,
    "end": 84.214,
    "idx": 142
  },
  {
    "char": "م",
    "start": 84.214,
    "end": 84.998,
    "idx": 143
  },
  {
    "char": "ا",
    "start": 84.998,
    "end": 85.446,
    "idx": 144
  },
  {
    "char": "ء",
    "start": 85.446,
    "end": 85.842,
    "idx": 145
  },
  {
    "char": "ك",
    "start": 86.023,
    "end": 86.119,
    "idx": 146
  },
  {
    "char": "ا",
    "start": 86.119,
    "end": 86.59899999999999,
    "idx": 147
  },
  {
    "char": "ل",
    "start": 86.59899999999999,
    "end": 86.791,
    "idx": 148
  },
  {
    "char": "م",
    "start": 86.791,
    "end": 86.919,
    "idx": 149
  },
  {
    "char": "ه",
    "start": 86.919,
    "end": 87.207,
    "idx": 150
  },
  {
    "char": "ل",
    "start": 87.207,
    "end": 87.565,
    "idx": 151
  },
  {
    "char": "و",
    "start": 90.262,
    "end": 90.326,
    "idx": 152
  },
  {
    "char": "ت",
    "start": 90.326,
    "end": 90.374,
    "idx": 153
  },
  {
    "char": "ك",
    "start": 90.374,
    "end": 90.518,
    "idx": 154
  },
  {
    "char": "و",
    "start": 90.518,
    "end": 90.63,
    "idx": 155
  },
  {
    "char": "ن",
    "start": 90.63,
    "end": 91.824,
    "idx": 156
  },
  {
    "char": "ا",
    "start": 92.125,
    "end": 92.349,
    "idx": 157
  },
  {
    "char": "ل",
    "start": 92.349,
    "end": 92.717,
    "idx": 158
  },
  {
    "char": "ج",
    "start": 92.717,
    "end": 92.973,
    "idx": 159
  },
  {
    "char": "ب",
    "start": 92.973,
    "end": 93.037,
    "idx": 160
  },
  {
    "char": "ا",
    "start": 93.037,
    "end": 93.213,
    "idx": 161
  },
  {
    "char": "ل",
    "start": 93.213,
    "end": 93.707,
    "idx": 162
  },
  {
    "char": "ك",
    "start": 93.927,
    "end": 94.07100000000001,
    "idx": 163
  },
  {
    "char": "ا",
    "start": 94.07100000000001,
    "end": 94.66300000000001,
    "idx": 164
  },
  {
    "char": "ل",
    "start": 94.66300000000001,
    "end": 94.855,
    "idx": 165
  },
  {
    "char": "ع",
    "start": 94.855,
    "end": 95.04700000000001,
    "idx": 166
  },
  {
    "char": "ه",
    "start": 95.04700000000001,
    "end": 98.40700000000001,
    "idx": 167
  },
  {
    "char": "ر",
    "start": 98.40700000000001,
    "end": 98.58300000000001,
    "idx": 168
  },
  {
    "char": "و",
    "start": 98.58300000000001,
    "end": 98.647,
    "idx": 169
  },
  {
    "char": "ل",
    "start": 98.647,
    "end": 99.031,
    "idx": 170
  },
  {
    "char": "ا",
    "start": 99.031,
    "end": 99.215,
    "idx": 171
  },
  {
    "char": "ي",
    "start": 99.355,
    "end": 99.563,
    "idx": 172
  },
  {
    "char": "س",
    "start": 99.563,
    "end": 100.107,
    "idx": 173
  },
  {
    "char": "أ",
    "start": 100.107,
    "end": 100.283,
    "idx": 174
  },
  {
    "char": "ل",
    "start": 100.283,
    "end": 100.677,
    "idx": 175
  },
  {
    "char": "ح",
    "start": 100.857,
    "end": 100.953,
    "idx": 176
  },
  {
    "char": "م",
    "start": 100.953,
    "end": 101.56099999999999,
    "idx": 177
  },
  {
    "char": "ي",
    "start": 101.56099999999999,
    "end": 101.817,
    "idx": 178
  },
  {
    "char": "م",
    "start": 101.817,
    "end": 102.169,
    "idx": 179
  },
  {
    "char": "ح",
    "start": 102.169,
    "end": 102.825,
    "idx": 180
  },
  {
    "char": "م",
    "start": 102.825,
    "end": 103.609,
    "idx": 181
  },
  {
    "char": "ي",
    "start": 103.609,
    "end": 103.817,
    "idx": 182
  },
  {
    "char": "م",
    "start": 103.817,
    "end": 104.377,
    "idx": 183
  },
  {
    "char": "ا",
    "start": 104.377,
    "end": 104.761,
    "idx": 184
  },
  {
    "char": "ي",
    "start": 104.761,
    "end": 106.777,
    "idx": 185
  },
  {
    "char": "ب",
    "start": 106.777,
    "end": 109.033,
    "idx": 186
  },
  {
    "char": "ص",
    "start": 109.033,
    "end": 109.449,
    "idx": 187
  },
  {
    "char": "ر",
    "start": 109.449,
    "end": 110.265,
    "idx": 188
  },
  {
    "char": "و",
    "start": 110.265,
    "end": 111.241,
    "idx": 189
  },
  {
    "char": "ن",
    "start": 111.241,
    "end": 111.417,
    "idx": 190
  },
  {
    "char": "ه",
    "start": 111.417,
    "end": 111.673,
    "idx": 191
  },
  {
    "char": "م",
    "start": 111.673,
    "end": 112.354,
    "idx": 192
  },
  {
    "char": "ي",
    "start": 115.827,
    "end": 116.099,
    "idx": 193
  },
  {
    "char": "و",
    "start": 116.099,
    "end": 116.259,
    "idx": 194
  },
  {
    "char": "د",
    "start": 116.259,
    "end": 117.075,
    "idx": 195
  },
  {
    "char": "ا",
    "start": 117.075,
    "end": 117.283,
    "idx": 196
  },
  {
    "char": "ل",
    "start": 117.283,
    "end": 117.411,
    "idx": 197
  },
  {
    "char": "م",
    "start": 117.411,
    "end": 117.923,
    "idx": 198
  },
  {
    "char": "ج",
    "start": 117.923,
    "end": 118.723,
    "idx": 199
  },
  {
    "char": "ر",
    "start": 118.723,
    "end": 119.363,
    "idx": 200
  },
  {
    "char": "م",
    "start": 119.363,
    "end": 119.523,
    "idx": 201
  },
  {
    "char": "ل",
    "start": 119.523,
    "end": 119.667,
    "idx": 202
  },
  {
    "char": "و",
    "start": 119.667,
    "end": 120.467,
    "idx": 203
  },
  {
    "char": "ي",
    "start": 120.467,
    "end": 120.931,
    "idx": 204
  },
  {
    "char": "ف",
    "start": 120.931,
    "end": 121.187,
    "idx": 205
  },
  {
    "char": "ت",
    "start": 121.187,
    "end": 121.587,
    "idx": 206
  },
  {
    "char": "د",
    "start": 121.587,
    "end": 121.955,
    "idx": 207
  },
  {
    "char": "ي",
    "start": 121.955,
    "end": 122.227,
    "idx": 208
  },
  {
    "char": "م",
    "start": 122.227,
    "end": 122.40299999999999,
    "idx": 209
  },
  {
    "char": "ن",
    "start": 122.40299999999999,
    "end": 122.956,
    "idx": 210
  },
  {
    "char": "ع",
    "start": 123.197,
    "end": 123.581,
    "idx": 211
  },
  {
    "char": "ذ",
    "start": 123.581,
    "end": 123.805,
    "idx": 212
  },
  {
    "char": "ا",
    "start": 123.805,
    "end": 124.093,
    "idx": 213
  },
  {
    "char": "ب",
    "start": 124.093,
    "end": 124.719,
    "idx": 214
  },
  {
    "char": "ي",
    "start": 124.839,
    "end": 125.67099999999999,
    "idx": 215
  },
  {
    "char": "و",
    "start": 125.67099999999999,
    "end": 125.943,
    "idx": 216
  },
  {
    "char": "م",
    "start": 125.943,
    "end": 126.343,
    "idx": 217
  },
  {
    "char": "ئ",
    "start": 126.343,
    "end": 126.887,
    "idx": 218
  },
  {
    "char": "ذ",
    "start": 126.887,
    "end": 127.903,
    "idx": 219
  },
  {
    "char": "ب",
    "start": 128.043,
    "end": 128.235,
    "idx": 220
  },
  {
    "char": "ب",
    "start": 128.235,
    "end": 129.083,
    "idx": 221
  },
  {
    "char": "ن",
    "start": 129.083,
    "end": 130.139,
    "idx": 222
  },
  {
    "char": "ي",
    "start": 130.139,
    "end": 130.603,
    "idx": 223
  },
  {
    "char": "ه",
    "start": 130.603,
    "end": 130.84300000000002,
    "idx": 224
  },
  {
    "char": "و",
    "start": 130.84300000000002,
    "end": 135.77100000000002,
    "idx": 225
  },
  {
    "char": "ص",
    "start": 135.77100000000002,
    "end": 136.155,
    "idx": 226
  },
  {
    "char": "ا",
    "start": 136.155,
    "end": 136.37900000000002,
    "idx": 227
  },
  {
    "char": "ح",
    "start": 136.37900000000002,
    "end": 136.89100000000002,
    "idx": 228
  },
  {
    "char": "ب",
    "start": 136.89100000000002,
    "end": 137.35500000000002,
    "idx": 229
  },
  {
    "char": "ت",
    "start": 137.35500000000002,
    "end": 137.707,
    "idx": 230
  },
  {
    "char": "ه",
    "start": 137.707,
    "end": 138.059,
    "idx": 231
  },
  {
    "char": "و",
    "start": 138.059,
    "end": 138.827,
    "idx": 232
  },
  {
    "char": "أ",
    "start": 138.827,
    "end": 139.227,
    "idx": 233
  },
  {
    "char": "خ",
    "start": 139.227,
    "end": 140.37900000000002,
    "idx": 234
  },
  {
    "char": "ي",
    "start": 140.37900000000002,
    "end": 140.603,
    "idx": 235
  },
  {
    "char": "ه",
    "start": 140.603,
    "end": 140.94,
    "idx": 236
  },
  {
    "char": "و",
    "start": 146.624,
    "end": 146.992,
    "idx": 237
  },
  {
    "char": "ف",
    "start": 146.992,
    "end": 147.184,
    "idx": 238
  },
  {
    "char": "ص",
    "start": 147.184,
    "end": 148.048,
    "idx": 239
  },
  {
    "char": "ي",
    "start": 148.048,
    "end": 148.512,
    "idx": 240
  },
  {
    "char": "ل",
    "start": 148.512,
    "end": 148.976,
    "idx": 241
  },
  {
    "char": "ت",
    "start": 148.976,
    "end": 149.31199999999998,
    "idx": 242
  },
  {
    "char": "ه",
    "start": 149.31199999999998,
    "end": 149.647,
    "idx": 243
  },
  {
    "char": "ا",
    "start": 149.907,
    "end": 150.115,
    "idx": 244
  },
  {
    "char": "ل",
    "start": 150.115,
    "end": 150.339,
    "idx": 245
  },
  {
    "char": "ت",
    "start": 150.339,
    "end": 150.70700000000002,
    "idx": 246
  },
  {
    "char": "ي",
    "start": 150.70700000000002,
    "end": 150.948,
    "idx": 247
  },
  {
    "char": "ت",
    "start": 151.129,
    "end": 151.91299999999998,
    "idx": 248
  },
  {
    "char": "ؤ",
    "start": 151.91299999999998,
    "end": 152.265,
    "idx": 249
  },
  {
    "char": "و",
    "start": 152.265,
    "end": 152.665,
    "idx": 250
  },
  {
    "char": "ي",
    "start": 152.665,
    "end": 153.35299999999998,
    "idx": 251
  },
  {
    "char": "ه",
    "start": 153.35299999999998,
    "end": 153.721,
    "idx": 252
  },
  {
    "char": "و",
    "start": 153.721,
    "end": 154.105,
    "idx": 253
  },
  {
    "char": "م",
    "start": 154.105,
    "end": 154.393,
    "idx": 254
  },
  {
    "char": "ن",
    "start": 154.393,
    "end": 154.58499999999998,
    "idx": 255
  },
  {
    "char": "ف",
    "start": 154.58499999999998,
    "end": 159.257,
    "idx": 256
  },
  {
    "char": "ي",
    "start": 159.257,
    "end": 159.785,
    "idx": 257
  },
  {
    "char": "ا",
    "start": 159.785,
    "end": 161.35299999999998,
    "idx": 258
  },
  {
    "char": "ل",
    "start": 161.35299999999998,
    "end": 161.689,
    "idx": 259
  },
  {
    "char": "أ",
    "start": 161.689,
    "end": 162.057,
    "idx": 260
  },
  {
    "char": "ر",
    "start": 162.057,
    "end": 162.441,
    "idx": 261
  },
  {
    "char": "ض",
    "start": 162.441,
    "end": 163.221,
    "idx": 262
  },
  {
    "char": "ج",
    "start": 163.341,
    "end": 163.67700000000002,
    "idx": 263
  },
  {
    "char": "م",
    "start": 163.67700000000002,
    "end": 164.60500000000002,
    "idx": 264
  },
  {
    "char": "ي",
    "start": 164.60500000000002,
    "end": 164.86100000000002,
    "idx": 265
  },
  {
    "char": "ع",
    "start": 164.86100000000002,
    "end": 165.853,
    "idx": 266
  },
  {
    "char": "ا",
    "start": 165.853,
    "end": 166.381,
    "idx": 267
  },
  {
    "char": "ث",
    "start": 166.381,
    "end": 167.549,
    "idx": 268
  },
  {
    "char": "م",
    "start": 167.549,
    "end": 167.646,
    "idx": 269
  },
  {
    "char": "ي",
    "start": 167.726,
    "end": 169.038,
    "idx": 270
  },
  {
    "char": "ن",
    "start": 169.038,
    "end": 169.566,
    "idx": 271
  },
  {
    "char": "ج",
    "start": 169.566,
    "end": 169.902,
    "idx": 272
  },
  {
    "char": "ي",
    "start": 169.902,
    "end": 170.809,
    "idx": 273
  },
  {
    "char": "ك",
    "start": 176.527,
    "end": 177.375,
    "idx": 274
  },
  {
    "char": "ل",
    "start": 177.375,
    "end": 177.743,
    "idx": 275
  },
  {
    "char": "ا",
    "start": 177.743,
    "end": 178.43099999999998,
    "idx": 276
  },
  {
    "char": "إ",
    "start": 178.43099999999998,
    "end": 178.84699999999998,
    "idx": 277
  },
  {
    "char": "ن",
    "start": 178.84699999999998,
    "end": 179.42299999999997,
    "idx": 278
  },
  {
    "char": "ه",
    "start": 179.42299999999997,
    "end": 180.99099999999999,
    "idx": 279
  },
  {
    "char": "ا",
    "start": 180.99099999999999,
    "end": 181.35899999999998,
    "idx": 280
  },
  {
    "char": "ل",
    "start": 181.35899999999998,
    "end": 182.063,
    "idx": 281
  },
  {
    "char": "غ",
    "start": 182.063,
    "end": 182.65499999999997,
    "idx": 282
  },
  {
    "char": "ا",
    "start": 182.65499999999997,
    "end": 183.05499999999998,
    "idx": 283
  },
  {
    "char": "ن",
    "start": 183.05499999999998,
    "end": 187.807,
    "idx": 284
  },
  {
    "char": "ز",
    "start": 187.807,
    "end": 188.815,
    "idx": 285
  },
  {
    "char": "ا",
    "start": 188.815,
    "end": 189.231,
    "idx": 286
  },
  {
    "char": "ع",
    "start": 189.231,
    "end": 189.66299999999998,
    "idx": 287
  },
  {
    "char": "ة",
    "start": 189.66299999999998,
    "end": 190.126,
    "idx": 288
  },
  {
    "char": "ل",
    "start": 190.607,
    "end": 190.799,
    "idx": 289
  },
  {
    "char": "ل",
    "start": 190.799,
    "end": 191.023,
    "idx": 290
  },
  {
    "char": "ش",
    "start": 191.023,
    "end": 191.391,
    "idx": 291
  },
  {
    "char": "و",
    "start": 191.391,
    "end": 192.015,
    "idx": 292
  },
  {
    "char": "ى",
    "start": 192.015,
    "end": 192.159,
    "idx": 293
  },
  {
    "char": "ت",
    "start": 192.159,
    "end": 192.351,
    "idx": 294
  },
  {
    "char": "د",
    "start": 192.351,
    "end": 196.207,
    "idx": 295
  },
  {
    "char": "ع",
    "start": 196.207,
    "end": 196.319,
    "idx": 296
  },
  {
    "char": "و",
    "start": 196.319,
    "end": 197.657,
    "idx": 297
  },
  {
    "char": "م",
    "start": 197.797,
    "end": 198.133,
    "idx": 298
  },
  {
    "char": "ن",
    "start": 198.133,
    "end": 198.538,
    "idx": 299
  },
  {
    "char": "أ",
    "start": 198.658,
    "end": 198.76999999999998,
    "idx": 300
  },
  {
    "char": "د",
    "start": 198.76999999999998,
    "end": 199.522,
    "idx": 301
  },
  {
    "char": "ب",
    "start": 199.522,
    "end": 199.85799999999998,
    "idx": 302
  },
  {
    "char": "ر",
    "start": 199.85799999999998,
    "end": 200.18,
    "idx": 303
  },
  {
    "char": "و",
    "start": 201.402,
    "end": 201.594,
    "idx": 304
  },
  {
    "char": "ت",
    "start": 201.594,
    "end": 202.23399999999998,
    "idx": 305
  },
  {
    "char": "و",
    "start": 202.23399999999998,
    "end": 202.39399999999998,
    "idx": 306
  },
  {
    "char": "ل",
    "start": 202.39399999999998,
    "end": 202.55399999999997,
    "idx": 307
  },
  {
    "char": "ى",
    "start": 202.55399999999997,
    "end": 202.804,
    "idx": 308
  },
  {
    "char": "وَ",
    "start": 205.94,
    "end": 206.132,
    "idx": 309
  },
  {
    "char": "جَ",
    "start": 206.132,
    "end": 206.692,
    "idx": 310
  },
  {
    "char": "مَ",
    "start": 206.692,
    "end": 206.884,
    "idx": 311
  },
  {
    "char": "عَ",
    "start": 206.884,
    "end": 207.09199999999998,
    "idx": 312
  },
  {
    "char": "فَ",
    "start": 207.09199999999998,
    "end": 207.34799999999998,
    "idx": 313
  },
  {
    "char": "أَ",
    "start": 207.34799999999998,
    "end": 207.796,
    "idx": 314
  },
  {
    "char": "وْ",
    "start": 207.796,
    "end": 208.052,
    "idx": 315
  },
  {
    "char": "عَ",
    "start": 208.052,
    "end": 208.66,
    "idx": 316
  },
  {
    "char": "ى",
    "start": 208.66,
    "end": 208.868,
    "idx": 317
  },
  {
    "char": "إِ",
    "start": 208.868,
    "end": 210.212,
    "idx": 318
  },
  {
    "char": "نَّ",
    "start": 210.212,
    "end": 213.55599999999998,
    "idx": 319
  },
  {
    "char": "ا",
    "start": 213.55599999999998,
    "end": 214.356,
    "idx": 320
  },
  {
    "char": "لْ",
    "start": 214.356,
    "end": 214.676,
    "idx": 321
  },
  {
    "char": "إِ",
    "start": 214.676,
    "end": 215.14,
    "idx": 322
  },
  {
    "char": "ن",
    "start": 215.14,
    "end": 216.324,
    "idx": 323
  },
  {
    "char": "سَ",
    "start": 216.324,
    "end": 216.628,
    "idx": 324
  },
  {
    "char": "ا",
    "start": 216.628,
    "end": 217.396,
    "idx": 325
  },
  {
    "char": "نَ",
    "start": 217.396,
    "end": 217.815,
    "idx": 326
  },
  {
    "char": "خُ",
    "start": 217.875,
    "end": 218.099,
    "idx": 327
  },
  {
    "char": "لِ",
    "start": 218.099,
    "end": 218.547,
    "idx": 328
  },
  {
    "char": "قَ",
    "start": 218.547,
    "end": 218.851,
    "idx": 329
  },
  {
    "char": "هَ",
    "start": 218.851,
    "end": 219.219,
    "idx": 330
  },
  {
    "char": "لُ",
    "start": 219.219,
    "end": 220.339,
    "idx": 331
  },
  {
    "char": "و",
    "start": 220.339,
    "end": 220.739,
    "idx": 332
  },
  {
    "char": "عً",
    "start": 220.739,
    "end": 220.931,
    "idx": 333
  },
  {
    "char": "ا",
    "start": 220.931,
    "end": 224.483,
    "idx": 334
  },
  {
    "char": "إِ",
    "start": 224.483,
    "end": 224.995,
    "idx": 335
  },
  {
    "char": "ذَ",
    "start": 224.995,
    "end": 225.299,
    "idx": 336
  },
  {
    "char": "ا",
    "start": 225.299,
    "end": 225.525,
    "idx": 337
  },
  {
    "char": "مَ",
    "start": 225.706,
    "end": 225.86599999999999,
    "idx": 338
  },
  {
    "char": "سَّ",
    "start": 225.86599999999999,
    "end": 226.81,
    "idx": 339
  },
  {
    "char": "هُ",
    "start": 226.81,
    "end": 227.168,
    "idx": 340
  },
  {
    "char": "ا",
    "start": 227.728,
    "end": 227.952,
    "idx": 341
  },
  {
    "char": "ل",
    "start": 227.952,
    "end": 228.08,
    "idx": 342
  },
  {
    "char": "شَّ",
    "start": 228.08,
    "end": 229.136,
    "idx": 343
  },
  {
    "char": "رُّ",
    "start": 229.136,
    "end": 229.392,
    "idx": 344
  },
  {
    "char": "جَ",
    "start": 229.392,
    "end": 230.06400000000002,
    "idx": 345
  },
  {
    "char": "زُ",
    "start": 230.06400000000002,
    "end": 230.192,
    "idx": 346
  },
  {
    "char": "و",
    "start": 230.192,
    "end": 230.78400000000002,
    "idx": 347
  },
  {
    "char": "عً",
    "start": 230.78400000000002,
    "end": 230.94400000000002,
    "idx": 348
  },
  {
    "char": "ا",
    "start": 230.94400000000002,
    "end": 231.373,
    "idx": 349
  },
  {
    "char": "و",
    "start": 233.362,
    "end": 233.48999999999998,
    "idx": 350
  },
  {
    "char": "إ",
    "start": 233.48999999999998,
    "end": 234.35399999999998,
    "idx": 351
  },
  {
    "char": "ذ",
    "start": 234.35399999999998,
    "end": 234.53,
    "idx": 352
  },
  {
    "char": "ا",
    "start": 234.53,
    "end": 234.722,
    "idx": 353
  },
  {
    "char": "م",
    "start": 234.722,
    "end": 234.834,
    "idx": 354
  },
  {
    "char": "س",
    "start": 234.834,
    "end": 235.682,
    "idx": 355
  },
  {
    "char": "ه",
    "start": 235.682,
    "end": 236.466,
    "idx": 356
  },
  {
    "char": "ا",
    "start": 236.546,
    "end": 236.802,
    "idx": 357
  },
  {
    "char": "ل",
    "start": 236.802,
    "end": 238.034,
    "idx": 358
  },
  {
    "char": "خ",
    "start": 238.034,
    "end": 238.082,
    "idx": 359
  },
  {
    "char": "ي",
    "start": 238.082,
    "end": 239.44199999999998,
    "idx": 360
  },
  {
    "char": "ر",
    "start": 239.44199999999998,
    "end": 239.89,
    "idx": 361
  },
  {
    "char": "م",
    "start": 239.89,
    "end": 241.32999999999998,
    "idx": 362
  },
  {
    "char": "ن",
    "start": 241.32999999999998,
    "end": 243.554,
    "idx": 363
  },
  {
    "char": "و",
    "start": 243.554,
    "end": 244.178,
    "idx": 364
  },
  {
    "char": "ع",
    "start": 244.178,
    "end": 244.482,
    "idx": 365
  },
  {
    "char": "ا",
    "start": 244.482,
    "end": 244.67399999999998,
    "idx": 366
  },
  {
    "char": "إ",
    "start": 244.67399999999998,
    "end": 245.12199999999999,
    "idx": 367
  },
  {
    "char": "ل",
    "start": 245.12199999999999,
    "end": 245.346,
    "idx": 368
  },
  {
    "char": "ا",
    "start": 245.346,
    "end": 246.242,
    "idx": 369
  },
  {
    "char": "ا",
    "start": 246.242,
    "end": 246.658,
    "idx": 370
  },
  {
    "char": "ل",
    "start": 246.658,
    "end": 247.106,
    "idx": 371
  },
  {
    "char": "م",
    "start": 247.106,
    "end": 247.218,
    "idx": 372
  },
  {
    "char": "ص",
    "start": 247.218,
    "end": 247.506,
    "idx": 373
  },
  {
    "char": "ل",
    "start": 247.506,
    "end": 247.938,
    "idx": 374
  },
  {
    "char": "ي",
    "start": 247.938,
    "end": 252.45,
    "idx": 375
  },
  {
    "char": "ن",
    "start": 252.45,
    "end": 253.23399999999998,
    "idx": 376
  },
  {
    "char": "ا",
    "start": 253.23399999999998,
    "end": 253.522,
    "idx": 377
  },
  {
    "char": "ل",
    "start": 253.522,
    "end": 253.89,
    "idx": 378
  },
  {
    "char": "ذ",
    "start": 253.89,
    "end": 254.20999999999998,
    "idx": 379
  },
  {
    "char": "ي",
    "start": 254.20999999999998,
    "end": 254.418,
    "idx": 380
  },
  {
    "char": "ن",
    "start": 254.418,
    "end": 254.594,
    "idx": 381
  },
  {
    "char": "ه",
    "start": 254.594,
    "end": 255.58599999999998,
    "idx": 382
  },
  {
    "char": "م",
    "start": 255.58599999999998,
    "end": 255.911,
    "idx": 383
  },
  {
    "char": "ع",
    "start": 255.991,
    "end": 256.135,
    "idx": 384
  },
  {
    "char": "ل",
    "start": 256.135,
    "end": 256.391,
    "idx": 385
  },
  {
    "char": "ى",
    "start": 256.391,
    "end": 256.531,
    "idx": 386
  },
  {
    "char": "ص",
    "start": 256.892,
    "end": 257.02,
    "idx": 387
  },
  {
    "char": "ل",
    "start": 257.02,
    "end": 257.212,
    "idx": 388
  },
  {
    "char": "ا",
    "start": 257.212,
    "end": 257.676,
    "idx": 389
  },
  {
    "char": "ت",
    "start": 257.676,
    "end": 257.9,
    "idx": 390
  },
  {
    "char": "ه",
    "start": 257.9,
    "end": 258.316,
    "idx": 391
  },
  {
    "char": "م",
    "start": 258.316,
    "end": 258.652,
    "idx": 392
  },
  {
    "char": "د",
    "start": 258.652,
    "end": 259.1,
    "idx": 393
  },
  {
    "char": "ا",
    "start": 259.1,
    "end": 259.628,
    "idx": 394
  },
  {
    "char": "ئ",
    "start": 259.628,
    "end": 260.796,
    "idx": 395
  },
  {
    "char": "م",
    "start": 260.796,
    "end": 261.068,
    "idx": 396
  },
  {
    "char": "ا",
    "start": 261.068,
    "end": 261.478,
    "idx": 397
  },
  {
    "char": "و",
    "start": 268.057,
    "end": 268.153,
    "idx": 398
  },
  {
    "char": "ا",
    "start": 268.153,
    "end": 268.90500000000003,
    "idx": 399
  },
  {
    "char": "ل",
    "start": 268.90500000000003,
    "end": 269.433,
    "idx": 400
  },
  {
    "char": "ذ",
    "start": 269.433,
    "end": 269.70500000000004,
    "idx": 401
  },
  {
    "char": "ي",
    "start": 269.70500000000004,
    "end": 269.945,
    "idx": 402
  },
  {
    "char": "ن",
    "start": 269.945,
    "end": 270.059,
    "idx": 403
  },
  {
    "char": "ف",
    "start": 270.28,
    "end": 270.952,
    "idx": 404
  },
  {
    "char": "ي",
    "start": 270.952,
    "end": 271.721,
    "idx": 405
  },
  {
    "char": "أ",
    "start": 271.802,
    "end": 272.618,
    "idx": 406
  },
  {
    "char": "م",
    "start": 272.618,
    "end": 272.778,
    "idx": 407
  },
  {
    "char": "و",
    "start": 272.778,
    "end": 272.98600000000005,
    "idx": 408
  },
  {
    "char": "ا",
    "start": 272.98600000000005,
    "end": 273.386,
    "idx": 409
  },
  {
    "char": "ل",
    "start": 273.386,
    "end": 273.642,
    "idx": 410
  },
  {
    "char": "ه",
    "start": 273.642,
    "end": 273.834,
    "idx": 411
  },
  {
    "char": "م",
    "start": 273.834,
    "end": 274.385,
    "idx": 412
  },
  {
    "char": "ح",
    "start": 274.505,
    "end": 274.617,
    "idx": 413
  },
  {
    "char": "ق",
    "start": 274.617,
    "end": 275.977,
    "idx": 414
  },
  {
    "char": "م",
    "start": 275.977,
    "end": 276.841,
    "idx": 415
  },
  {
    "char": "ع",
    "start": 276.841,
    "end": 277.737,
    "idx": 416
  },
  {
    "char": "ل",
    "start": 277.737,
    "end": 278.29699999999997,
    "idx": 417
  },
  {
    "char": "و",
    "start": 278.29699999999997,
    "end": 278.489,
    "idx": 418
  },
  {
    "char": "م",
    "start": 278.489,
    "end": 279.129,
    "idx": 419
  },
  {
    "char": "ل",
    "start": 279.129,
    "end": 279.497,
    "idx": 420
  },
  {
    "char": "ل",
    "start": 279.497,
    "end": 280.521,
    "idx": 421
  },
  {
    "char": "س",
    "start": 280.521,
    "end": 283.673,
    "idx": 422
  },
  {
    "char": "ا",
    "start": 283.673,
    "end": 284.233,
    "idx": 423
  },
  {
    "char": "ئ",
    "start": 284.233,
    "end": 284.697,
    "idx": 424
  },
  {
    "char": "ل",
    "start": 284.697,
    "end": 285.177,
    "idx": 425
  },
  {
    "char": "و",
    "start": 285.177,
    "end": 285.609,
    "idx": 426
  },
  {
    "char": "ا",
    "start": 285.609,
    "end": 285.849,
    "idx": 427
  },
  {
    "char": "ل",
    "start": 285.849,
    "end": 286.105,
    "idx": 428
  },
  {
    "char": "م",
    "start": 286.105,
    "end": 286.841,
    "idx": 429
  },
  {
    "char": "ح",
    "start": 286.841,
    "end": 287.529,
    "idx": 430
  },
  {
    "char": "ر",
    "start": 287.529,
    "end": 287.993,
    "idx": 431
  },
  {
    "char": "و",
    "start": 287.993,
    "end": 288.489,
    "idx": 432
  },
  {
    "char": "م",
    "start": 288.489,
    "end": 291.145,
    "idx": 433
  },
  {
    "char": "و",
    "start": 296.052,
    "end": 296.708,
    "idx": 434
  },
  {
    "char": "ا",
    "start": 296.708,
    "end": 297.028,
    "idx": 435
  },
  {
    "char": "ل",
    "start": 297.028,
    "end": 297.428,
    "idx": 436
  },
  {
    "char": "ذ",
    "start": 297.428,
    "end": 297.50800000000004,
    "idx": 437
  },
  {
    "char": "ي",
    "start": 297.50800000000004,
    "end": 297.79600000000005,
    "idx": 438
  },
  {
    "char": "ن",
    "start": 297.79600000000005,
    "end": 297.975,
    "idx": 439
  },
  {
    "char": "ي",
    "start": 298.075,
    "end": 298.347,
    "idx": 440
  },
  {
    "char": "ص",
    "start": 298.347,
    "end": 299.291,
    "idx": 441
  },
  {
    "char": "د",
    "start": 299.291,
    "end": 299.45099999999996,
    "idx": 442
  },
  {
    "char": "ق",
    "start": 299.45099999999996,
    "end": 299.627,
    "idx": 443
  },
  {
    "char": "و",
    "start": 299.627,
    "end": 300.395,
    "idx": 444
  },
  {
    "char": "ن",
    "start": 300.395,
    "end": 300.598,
    "idx": 445
  },
  {
    "char": "ب",
    "start": 300.878,
    "end": 301.198,
    "idx": 446
  },
  {
    "char": "ي",
    "start": 301.198,
    "end": 302.142,
    "idx": 447
  },
  {
    "char": "و",
    "start": 302.142,
    "end": 302.798,
    "idx": 448
  },
  {
    "char": "م",
    "start": 302.798,
    "end": 303.15,
    "idx": 449
  },
  {
    "char": "ا",
    "start": 303.15,
    "end": 303.63,
    "idx": 450
  },
  {
    "char": "ل",
    "start": 303.63,
    "end": 303.88599999999997,
    "idx": 451
  },
  {
    "char": "د",
    "start": 303.88599999999997,
    "end": 304.558,
    "idx": 452
  },
  {
    "char": "ي",
    "start": 304.558,
    "end": 304.71799999999996,
    "idx": 453
  },
  {
    "char": "ن",
    "start": 304.71799999999996,
    "end": 304.86199999999997,
    "idx": 454
  },
  {
    "char": "و",
    "start": 304.86199999999997,
    "end": 305.534,
    "idx": 455
  },
  {
    "char": "ا",
    "start": 305.534,
    "end": 307.102,
    "idx": 456
  },
  {
    "char": "ل",
    "start": 307.102,
    "end": 311.454,
    "idx": 457
  },
  {
    "char": "ذ",
    "start": 311.454,
    "end": 312.046,
    "idx": 458
  },
  {
    "char": "ي",
    "start": 312.046,
    "end": 312.414,
    "idx": 459
  },
  {
    "char": "ن",
    "start": 312.414,
    "end": 312.62199999999996,
    "idx": 460
  },
  {
    "char": "ه",
    "start": 312.62199999999996,
    "end": 313.086,
    "idx": 461
  },
  {
    "char": "م",
    "start": 313.086,
    "end": 314.296,
    "idx": 462
  },
  {
    "char": "م",
    "start": 314.356,
    "end": 314.468,
    "idx": 463
  },
  {
    "char": "ن",
    "start": 314.468,
    "end": 315.077,
    "idx": 464
  },
  {
    "char": "ع",
    "start": 315.197,
    "end": 315.565,
    "idx": 465
  },
  {
    "char": "ذ",
    "start": 315.565,
    "end": 316.061,
    "idx": 466
  },
  {
    "char": "ا",
    "start": 316.061,
    "end": 316.765,
    "idx": 467
  },
  {
    "char": "ب",
    "start": 316.765,
    "end": 317.099,
    "idx": 468
  },
  {
    "char": "ر",
    "start": 317.62,
    "end": 317.764,
    "idx": 469
  },
  {
    "char": "ب",
    "start": 317.764,
    "end": 318.116,
    "idx": 470
  },
  {
    "char": "ه",
    "start": 318.116,
    "end": 318.75600000000003,
    "idx": 471
  },
  {
    "char": "م",
    "start": 318.75600000000003,
    "end": 319.483,
    "idx": 472
  },
  {
    "char": "م",
    "start": 320.043,
    "end": 320.331,
    "idx": 473
  },
  {
    "char": "ش",
    "start": 320.331,
    "end": 321.067,
    "idx": 474
  },
  {
    "char": "ف",
    "start": 321.067,
    "end": 321.307,
    "idx": 475
  },
  {
    "char": "ق",
    "start": 321.307,
    "end": 321.819,
    "idx": 476
  },
  {
    "char": "و",
    "start": 321.819,
    "end": 322.299,
    "idx": 477
  },
  {
    "char": "ن",
    "start": 322.299,
    "end": 322.887,
    "idx": 478
  },
  {
    "char": "و",
    "start": 328.992,
    "end": 329.088,
    "idx": 479
  },
  {
    "char": "ع",
    "start": 329.088,
    "end": 329.456,
    "idx": 480
  },
  {
    "char": "ذ",
    "start": 329.456,
    "end": 329.56800000000004,
    "idx": 481
  },
  {
    "char": "ا",
    "start": 329.56800000000004,
    "end": 329.84000000000003,
    "idx": 482
  },
  {
    "char": "ب",
    "start": 329.84000000000003,
    "end": 329.92,
    "idx": 483
  },
  {
    "char": "ر",
    "start": 329.92,
    "end": 330.30400000000003,
    "idx": 484
  },
  {
    "char": "ب",
    "start": 330.30400000000003,
    "end": 331.32800000000003,
    "idx": 485
  },
  {
    "char": "ه",
    "start": 331.32800000000003,
    "end": 331.88800000000003,
    "idx": 486
  },
  {
    "char": "م",
    "start": 331.88800000000003,
    "end": 332.399,
    "idx": 487
  },
  {
    "char": "غ",
    "start": 332.579,
    "end": 332.755,
    "idx": 488
  },
  {
    "char": "ي",
    "start": 332.755,
    "end": 333.235,
    "idx": 489
  },
  {
    "char": "ر",
    "start": 333.235,
    "end": 333.662,
    "idx": 490
  },
  {
    "char": "م",
    "start": 333.742,
    "end": 333.838,
    "idx": 491
  },
  {
    "char": "أ",
    "start": 333.838,
    "end": 333.85400000000004,
    "idx": 492
  },
  {
    "char": "م",
    "start": 333.85400000000004,
    "end": 334.494,
    "idx": 493
  },
  {
    "char": "و",
    "start": 334.494,
    "end": 336.942,
    "idx": 494
  },
  {
    "char": "ن",
    "start": 336.942,
    "end": 339.166,
    "idx": 495
  },
  {
    "char": "و",
    "start": 339.166,
    "end": 339.838,
    "idx": 496
  },
  {
    "char": "ا",
    "start": 339.838,
    "end": 340.238,
    "idx": 497
  },
  {
    "char": "ل",
    "start": 340.238,
    "end": 340.526,
    "idx": 498
  },
  {
    "char": "ذ",
    "start": 340.526,
    "end": 340.702,
    "idx": 499
  },
  {
    "char": "ي",
    "start": 340.702,
    "end": 340.942,
    "idx": 500
  },
  {
    "char": "ن",
    "start": 340.942,
    "end": 341.822,
    "idx": 501
  },
  {
    "char": "ه",
    "start": 341.822,
    "end": 341.966,
    "idx": 502
  },
  {
    "char": "م",
    "start": 341.966,
    "end": 342.17400000000004,
    "idx": 503
  },
  {
    "char": "ل",
    "start": 342.17400000000004,
    "end": 342.63800000000003,
    "idx": 504
  },
  {
    "char": "ف",
    "start": 342.63800000000003,
    "end": 343.31,
    "idx": 505
  },
  {
    "char": "ر",
    "start": 343.31,
    "end": 343.374,
    "idx": 506
  },
  {
    "char": "و",
    "start": 343.374,
    "end": 343.63,
    "idx": 507
  },
  {
    "char": "ج",
    "start": 343.63,
    "end": 343.87,
    "idx": 508
  },
  {
    "char": "ه",
    "start": 343.87,
    "end": 344.014,
    "idx": 509
  },
  {
    "char": "م",
    "start": 344.014,
    "end": 344.544,
    "idx": 510
  },
  {
    "char": "ح",
    "start": 344.664,
    "end": 344.936,
    "idx": 511
  },
  {
    "char": "ا",
    "start": 344.936,
    "end": 345.52799999999996,
    "idx": 512
  },
  {
    "char": "ف",
    "start": 345.52799999999996,
    "end": 346.424,
    "idx": 513
  },
  {
    "char": "ظ",
    "start": 346.424,
    "end": 347.01599999999996,
    "idx": 514
  },
  {
    "char": "و",
    "start": 347.01599999999996,
    "end": 348.536,
    "idx": 515
  },
  {
    "char": "ن",
    "start": 348.536,
    "end": 349.414,
    "idx": 516
  },
  {
    "char": "إ",
    "start": 353.731,
    "end": 354.49899999999997,
    "idx": 517
  },
  {
    "char": "ل",
    "start": 354.49899999999997,
    "end": 354.723,
    "idx": 518
  },
  {
    "char": "ا",
    "start": 354.723,
    "end": 355.027,
    "idx": 519
  },
  {
    "char": "ع",
    "start": 355.027,
    "end": 355.203,
    "idx": 520
  },
  {
    "char": "ل",
    "start": 355.203,
    "end": 355.491,
    "idx": 521
  },
  {
    "char": "ى",
    "start": 355.491,
    "end": 355.827,
    "idx": 522
  },
  {
    "char": "أ",
    "start": 355.827,
    "end": 356.403,
    "idx": 523
  },
  {
    "char": "ز",
    "start": 356.403,
    "end": 356.979,
    "idx": 524
  },
  {
    "char": "و",
    "start": 356.979,
    "end": 357.411,
    "idx": 525
  },
  {
    "char": "ا",
    "start": 357.411,
    "end": 358.611,
    "idx": 526
  },
  {
    "char": "ج",
    "start": 358.611,
    "end": 359.491,
    "idx": 527
  },
  {
    "char": "ه",
    "start": 359.491,
    "end": 359.667,
    "idx": 528
  },
  {
    "char": "م",
    "start": 359.667,
    "end": 360.003,
    "idx": 529
  },
  {
    "char": "أ",
    "start": 360.003,
    "end": 360.307,
    "idx": 530
  },
  {
    "char": "و",
    "start": 360.307,
    "end": 361.083,
    "idx": 531
  },
  {
    "char": "م",
    "start": 361.183,
    "end": 361.327,
    "idx": 532
  },
  {
    "char": "ا",
    "start": 361.327,
    "end": 361.43899999999996,
    "idx": 533
  },
  {
    "char": "م",
    "start": 361.43899999999996,
    "end": 361.711,
    "idx": 534
  },
  {
    "char": "ل",
    "start": 361.711,
    "end": 362.04699999999997,
    "idx": 535
  },
  {
    "char": "ك",
    "start": 362.04699999999997,
    "end": 362.143,
    "idx": 536
  },
  {
    "char": "ت",
    "start": 362.143,
    "end": 362.431,
    "idx": 537
  },
  {
    "char": "أ",
    "start": 362.431,
    "end": 362.799,
    "idx": 538
  },
  {
    "char": "ي",
    "start": 362.799,
    "end": 363.455,
    "idx": 539
  },
  {
    "char": "م",
    "start": 363.455,
    "end": 363.695,
    "idx": 540
  },
  {
    "char": "ا",
    "start": 363.695,
    "end": 364.60699999999997,
    "idx": 541
  },
  {
    "char": "ن",
    "start": 364.60699999999997,
    "end": 364.895,
    "idx": 542
  },
  {
    "char": "ه",
    "start": 364.895,
    "end": 365.007,
    "idx": 543
  },
  {
    "char": "م",
    "start": 365.007,
    "end": 366.472,
    "idx": 544
  },
  {
    "char": "ف",
    "start": 366.632,
    "end": 366.824,
    "idx": 545
  },
  {
    "char": "إ",
    "start": 366.824,
    "end": 367.128,
    "idx": 546
  },
  {
    "char": "ن",
    "start": 367.128,
    "end": 368.36,
    "idx": 547
  },
  {
    "char": "ه",
    "start": 368.36,
    "end": 368.728,
    "idx": 548
  },
  {
    "char": "م",
    "start": 368.728,
    "end": 369.417,
    "idx": 549
  },
  {
    "char": "غ",
    "start": 369.577,
    "end": 369.865,
    "idx": 550
  },
  {
    "char": "ي",
    "start": 369.865,
    "end": 370.713,
    "idx": 551
  },
  {
    "char": "ر",
    "start": 370.713,
    "end": 371.753,
    "idx": 552
  },
  {
    "char": "م",
    "start": 371.753,
    "end": 372.537,
    "idx": 553
  },
  {
    "char": "ل",
    "start": 372.537,
    "end": 373.017,
    "idx": 554
  },
  {
    "char": "و",
    "start": 373.017,
    "end": 373.561,
    "idx": 555
  },
  {
    "char": "م",
    "start": 373.561,
    "end": 374.089,
    "idx": 556
  },
  {
    "char": "ي",
    "start": 374.089,
    "end": 374.537,
    "idx": 557
  },
  {
    "char": "ن",
    "start": 374.537,
    "end": 374.946,
    "idx": 558
  },
  {
    "char": "ف",
    "start": 377.204,
    "end": 377.41200000000003,
    "idx": 559
  },
  {
    "char": "م",
    "start": 377.41200000000003,
    "end": 378.036,
    "idx": 560
  },
  {
    "char": "ن",
    "start": 378.036,
    "end": 378.567,
    "idx": 561
  },
  {
    "char": "ا",
    "start": 378.627,
    "end": 379.427,
    "idx": 562
  },
  {
    "char": "ب",
    "start": 379.427,
    "end": 379.85900000000004,
    "idx": 563
  },
  {
    "char": "ت",
    "start": 379.85900000000004,
    "end": 380.707,
    "idx": 564
  },
  {
    "char": "غ",
    "start": 380.707,
    "end": 381.939,
    "idx": 565
  },
  {
    "char": "ى",
    "start": 381.939,
    "end": 382.695,
    "idx": 566
  },
  {
    "char": "و",
    "start": 383.276,
    "end": 383.43600000000004,
    "idx": 567
  },
  {
    "char": "ر",
    "start": 383.43600000000004,
    "end": 383.452,
    "idx": 568
  },
  {
    "char": "ا",
    "start": 383.452,
    "end": 383.612,
    "idx": 569
  },
  {
    "char": "ء",
    "start": 383.612,
    "end": 383.836,
    "idx": 570
  },
  {
    "char": "ذ",
    "start": 383.836,
    "end": 384.124,
    "idx": 571
  },
  {
    "char": "ل",
    "start": 384.124,
    "end": 384.172,
    "idx": 572
  },
  {
    "char": "ك",
    "start": 384.172,
    "end": 384.539,
    "idx": 573
  },
  {
    "char": "ف",
    "start": 384.719,
    "end": 384.97499999999997,
    "idx": 574
  },
  {
    "char": "أ",
    "start": 384.97499999999997,
    "end": 385.743,
    "idx": 575
  },
  {
    "char": "و",
    "start": 385.743,
    "end": 386.079,
    "idx": 576
  },
  {
    "char": "ل",
    "start": 386.079,
    "end": 387.039,
    "idx": 577
  },
  {
    "char": "ئ",
    "start": 387.039,
    "end": 387.935,
    "idx": 578
  },
  {
    "char": "ك",
    "start": 387.935,
    "end": 388.327,
    "idx": 579
  },
  {
    "char": "ه",
    "start": 388.848,
    "end": 389.05600000000004,
    "idx": 580
  },
  {
    "char": "م",
    "start": 389.05600000000004,
    "end": 389.149,
    "idx": 581
  },
  {
    "char": "ا",
    "start": 389.349,
    "end": 389.84499999999997,
    "idx": 582
  },
  {
    "char": "ل",
    "start": 389.84499999999997,
    "end": 390.149,
    "idx": 583
  },
  {
    "char": "ع",
    "start": 390.149,
    "end": 390.917,
    "idx": 584
  },
  {
    "char": "ا",
    "start": 390.917,
    "end": 391.557,
    "idx": 585
  },
  {
    "char": "د",
    "start": 391.557,
    "end": 392.149,
    "idx": 586
  },
  {
    "char": "و",
    "start": 392.149,
    "end": 392.885,
    "idx": 587
  },
  {
    "char": "ن",
    "start": 392.885,
    "end": 393.778,
    "idx": 588
  },
  {
    "char": "و",
    "start": 398.467,
    "end": 398.531,
    "idx": 589
  },
  {
    "char": "ا",
    "start": 398.531,
    "end": 399.01099999999997,
    "idx": 590
  },
  {
    "char": "ل",
    "start": 399.01099999999997,
    "end": 399.251,
    "idx": 591
  },
  {
    "char": "ذ",
    "start": 399.251,
    "end": 399.587,
    "idx": 592
  },
  {
    "char": "ي",
    "start": 399.587,
    "end": 399.827,
    "idx": 593
  },
  {
    "char": "ن",
    "start": 399.827,
    "end": 399.923,
    "idx": 594
  },
  {
    "char": "ه",
    "start": 399.923,
    "end": 400.787,
    "idx": 595
  },
  {
    "char": "م",
    "start": 400.787,
    "end": 401.211,
    "idx": 596
  },
  {
    "char": "ل",
    "start": 401.651,
    "end": 401.76300000000003,
    "idx": 597
  },
  {
    "char": "أ",
    "start": 401.76300000000003,
    "end": 401.987,
    "idx": 598
  },
  {
    "char": "م",
    "start": 401.987,
    "end": 402.163,
    "idx": 599
  },
  {
    "char": "ا",
    "start": 402.163,
    "end": 402.387,
    "idx": 600
  },
  {
    "char": "ن",
    "start": 402.387,
    "end": 402.723,
    "idx": 601
  },
  {
    "char": "ا",
    "start": 402.723,
    "end": 403.25100000000003,
    "idx": 602
  },
  {
    "char": "ت",
    "start": 403.25100000000003,
    "end": 403.603,
    "idx": 603
  },
  {
    "char": "ه",
    "start": 403.603,
    "end": 403.683,
    "idx": 604
  },
  {
    "char": "م",
    "start": 403.683,
    "end": 403.843,
    "idx": 605
  },
  {
    "char": "و",
    "start": 403.843,
    "end": 404.595,
    "idx": 606
  },
  {
    "char": "ع",
    "start": 404.595,
    "end": 404.73900000000003,
    "idx": 607
  },
  {
    "char": "ه",
    "start": 404.73900000000003,
    "end": 405.25100000000003,
    "idx": 608
  },
  {
    "char": "د",
    "start": 405.25100000000003,
    "end": 405.85900000000004,
    "idx": 609
  },
  {
    "char": "ه",
    "start": 405.85900000000004,
    "end": 406.259,
    "idx": 610
  },
  {
    "char": "م",
    "start": 406.259,
    "end": 406.778,
    "idx": 611
  },
  {
    "char": "ر",
    "start": 407.039,
    "end": 407.167,
    "idx": 612
  },
  {
    "char": "ا",
    "start": 407.167,
    "end": 407.58299999999997,
    "idx": 613
  },
  {
    "char": "ع",
    "start": 407.58299999999997,
    "end": 407.80699999999996,
    "idx": 614
  },
  {
    "char": "و",
    "start": 407.80699999999996,
    "end": 409.007,
    "idx": 615
  },
  {
    "char": "ن",
    "start": 409.007,
    "end": 410.623,
    "idx": 616
  },
  {
    "char": "و",
    "start": 410.623,
    "end": 414.751,
    "idx": 617
  },
  {
    "char": "ا",
    "start": 414.751,
    "end": 415.551,
    "idx": 618
  },
  {
    "char": "ل",
    "start": 415.551,
    "end": 415.919,
    "idx": 619
  },
  {
    "char": "ذ",
    "start": 415.919,
    "end": 416.255,
    "idx": 620
  },
  {
    "char": "ي",
    "start": 416.255,
    "end": 416.55899999999997,
    "idx": 621
  },
  {
    "char": "ن",
    "start": 416.55899999999997,
    "end": 416.87899999999996,
    "idx": 622
  },
  {
    "char": "ه",
    "start": 416.87899999999996,
    "end": 418.031,
    "idx": 623
  },
  {
    "char": "م",
    "start": 418.031,
    "end": 418.334,
    "idx": 624
  },
  {
    "char": "ب",
    "start": 418.454,
    "end": 418.694,
    "idx": 625
  },
  {
    "char": "ش",
    "start": 418.694,
    "end": 419.07800000000003,
    "idx": 626
  },
  {
    "char": "ه",
    "start": 419.07800000000003,
    "end": 419.382,
    "idx": 627
  },
  {
    "char": "ا",
    "start": 419.382,
    "end": 419.862,
    "idx": 628
  },
  {
    "char": "د",
    "start": 419.862,
    "end": 420.214,
    "idx": 629
  },
  {
    "char": "ا",
    "start": 420.214,
    "end": 420.422,
    "idx": 630
  },
  {
    "char": "ت",
    "start": 420.422,
    "end": 420.742,
    "idx": 631
  },
  {
    "char": "ه",
    "start": 420.742,
    "end": 421.286,
    "idx": 632
  },
  {
    "char": "م",
    "start": 421.286,
    "end": 421.979,
    "idx": 633
  },
  {
    "char": "ق",
    "start": 422.18,
    "end": 422.75600000000003,
    "idx": 634
  },
  {
    "char": "ا",
    "start": 422.75600000000003,
    "end": 423.62,
    "idx": 635
  },
  {
    "char": "ئ",
    "start": 423.62,
    "end": 424.26,
    "idx": 636
  },
  {
    "char": "م",
    "start": 424.26,
    "end": 425.572,
    "idx": 637
  },
  {
    "char": "و",
    "start": 425.572,
    "end": 426.75600000000003,
    "idx": 638
  },
  {
    "char": "ن",
    "start": 426.75600000000003,
    "end": 427.647,
    "idx": 639
  },
  {
    "char": "و",
    "start": 431.727,
    "end": 431.791,
    "idx": 640
  },
  {
    "char": "ا",
    "start": 431.791,
    "end": 432.41499999999996,
    "idx": 641
  },
  {
    "char": "ل",
    "start": 432.41499999999996,
    "end": 432.68699999999995,
    "idx": 642
  },
  {
    "char": "ذ",
    "start": 432.68699999999995,
    "end": 433.10299999999995,
    "idx": 643
  },
  {
    "char": "ي",
    "start": 433.10299999999995,
    "end": 433.359,
    "idx": 644
  },
  {
    "char": "ن",
    "start": 433.359,
    "end": 433.41,
    "idx": 645
  },
  {
    "char": "ه",
    "start": 433.49,
    "end": 433.81,
    "idx": 646
  },
  {
    "char": "م",
    "start": 433.81,
    "end": 434.562,
    "idx": 647
  },
  {
    "char": "ع",
    "start": 434.562,
    "end": 434.866,
    "idx": 648
  },
  {
    "char": "ل",
    "start": 434.866,
    "end": 435.122,
    "idx": 649
  },
  {
    "char": "ى",
    "start": 435.122,
    "end": 435.314,
    "idx": 650
  },
  {
    "char": "ص",
    "start": 435.314,
    "end": 435.682,
    "idx": 651
  },
  {
    "char": "ل",
    "start": 435.682,
    "end": 436.05,
    "idx": 652
  },
  {
    "char": "ا",
    "start": 436.05,
    "end": 436.338,
    "idx": 653
  },
  {
    "char": "ت",
    "start": 436.338,
    "end": 436.978,
    "idx": 654
  },
  {
    "char": "ه",
    "start": 436.978,
    "end": 437.23400000000004,
    "idx": 655
  },
  {
    "char": "م",
    "start": 437.23400000000004,
    "end": 437.878,
    "idx": 656
  },
  {
    "char": "ي",
    "start": 437.998,
    "end": 438.366,
    "idx": 657
  },
  {
    "char": "ح",
    "start": 438.366,
    "end": 438.606,
    "idx": 658
  },
  {
    "char": "ا",
    "start": 438.606,
    "end": 439.198,
    "idx": 659
  },
  {
    "char": "ف",
    "start": 439.198,
    "end": 439.95,
    "idx": 660
  },
  {
    "char": "ظ",
    "start": 439.95,
    "end": 442.44599999999997,
    "idx": 661
  },
  {
    "char": "و",
    "start": 442.44599999999997,
    "end": 444.90999999999997,
    "idx": 662
  },
  {
    "char": "ن",
    "start": 444.90999999999997,
    "end": 445.294,
    "idx": 663
  },
  {
    "char": "أ",
    "start": 445.294,
    "end": 445.78999999999996,
    "idx": 664
  },
  {
    "char": "و",
    "start": 445.78999999999996,
    "end": 446.366,
    "idx": 665
  },
  {
    "char": "ل",
    "start": 446.366,
    "end": 446.894,
    "idx": 666
  },
  {
    "char": "ئ",
    "start": 446.894,
    "end": 447.166,
    "idx": 667
  },
  {
    "char": "ك",
    "start": 447.166,
    "end": 447.414,
    "idx": 668
  },
  {
    "char": "ف",
    "start": 447.635,
    "end": 448.03499999999997,
    "idx": 669
  },
  {
    "char": "ي",
    "start": 448.03499999999997,
    "end": 448.356,
    "idx": 670
  },
  {
    "char": "ج",
    "start": 448.496,
    "end": 448.57599999999996,
    "idx": 671
  },
  {
    "char": "ن",
    "start": 448.57599999999996,
    "end": 449.792,
    "idx": 672
  },
  {
    "char": "ا",
    "start": 449.792,
    "end": 450.08,
    "idx": 673
  },
  {
    "char": "ت",
    "start": 450.08,
    "end": 450.544,
    "idx": 674
  },
  {
    "char": "م",
    "start": 450.544,
    "end": 451.03999999999996,
    "idx": 675
  },
  {
    "char": "ك",
    "start": 451.03999999999996,
    "end": 451.84,
    "idx": 676
  },
  {
    "char": "ر",
    "start": 451.84,
    "end": 452.43199999999996,
    "idx": 677
  },
  {
    "char": "م",
    "start": 452.43199999999996,
    "end": 452.71999999999997,
    "idx": 678
  },
  {
    "char": "و",
    "start": 452.71999999999997,
    "end": 453.08799999999997,
    "idx": 679
  },
  {
    "char": "ن",
    "start": 453.08799999999997,
    "end": 455.288,
    "idx": 680
  },
  {
    "char": "فَ",
    "start": 458.913,
    "end": 459.297,
    "idx": 681
  },
  {
    "char": "مَ",
    "start": 459.297,
    "end": 459.617,
    "idx": 682
  },
  {
    "char": "ا",
    "start": 459.617,
    "end": 459.777,
    "idx": 683
  },
  {
    "char": "لِ",
    "start": 459.777,
    "end": 459.969,
    "idx": 684
  },
  {
    "char": "لَّ",
    "start": 459.969,
    "end": 460.14500000000004,
    "idx": 685
  },
  {
    "char": "ذِ",
    "start": 460.14500000000004,
    "end": 461.345,
    "idx": 686
  },
  {
    "char": "ي",
    "start": 461.345,
    "end": 462.225,
    "idx": 687
  },
  {
    "char": "نَ",
    "start": 462.225,
    "end": 462.38,
    "idx": 688
  },
  {
    "char": "كَ",
    "start": 462.6,
    "end": 462.824,
    "idx": 689
  },
  {
    "char": "فَ",
    "start": 462.824,
    "end": 463.096,
    "idx": 690
  },
  {
    "char": "رُ",
    "start": 463.096,
    "end": 463.32000000000005,
    "idx": 691
  },
  {
    "char": "و",
    "start": 463.32000000000005,
    "end": 463.704,
    "idx": 692
  },
  {
    "char": "ا",
    "start": 463.704,
    "end": 464.043,
    "idx": 693
  },
  {
    "char": "قِ",
    "start": 464.223,
    "end": 464.75100000000003,
    "idx": 694
  },
  {
    "char": "بَ",
    "start": 464.75100000000003,
    "end": 465.103,
    "idx": 695
  },
  {
    "char": "لَ",
    "start": 465.103,
    "end": 466.543,
    "idx": 696
  },
  {
    "char": "كَ",
    "start": 466.543,
    "end": 467.039,
    "idx": 697
  },
  {
    "char": "مُ",
    "start": 467.039,
    "end": 467.503,
    "idx": 698
  },
  {
    "char": "هْ",
    "start": 467.503,
    "end": 468.031,
    "idx": 699
  },
  {
    "char": "طِ",
    "start": 468.031,
    "end": 468.175,
    "idx": 700
  },
  {
    "char": "عِ",
    "start": 468.175,
    "end": 468.607,
    "idx": 701
  },
  {
    "char": "ي",
    "start": 468.607,
    "end": 469.151,
    "idx": 702
  },
  {
    "char": "نَ",
    "start": 469.151,
    "end": 469.839,
    "idx": 703
  },
  {
    "char": "عَ",
    "start": 469.839,
    "end": 473.087,
    "idx": 704
  },
  {
    "char": "نِ",
    "start": 473.087,
    "end": 473.521,
    "idx": 705
  },
  {
    "char": "ا",
    "start": 473.982,
    "end": 474.35,
    "idx": 706
  },
  {
    "char": "لْ",
    "start": 474.35,
    "end": 474.70200000000006,
    "idx": 707
  },
  {
    "char": "يَ",
    "start": 474.70200000000006,
    "end": 474.894,
    "idx": 708
  },
  {
    "char": "مِ",
    "start": 474.894,
    "end": 475.02200000000005,
    "idx": 709
  },
  {
    "char": "ي",
    "start": 475.02200000000005,
    "end": 475.24600000000004,
    "idx": 710
  },
  {
    "char": "نِ",
    "start": 475.24600000000004,
    "end": 475.405,
    "idx": 711
  },
  {
    "char": "وَ",
    "start": 475.605,
    "end": 475.89300000000003,
    "idx": 712
  },
  {
    "char": "عَ",
    "start": 475.89300000000003,
    "end": 476.069,
    "idx": 713
  },
  {
    "char": "نِ",
    "start": 476.069,
    "end": 476.427,
    "idx": 714
  },
  {
    "char": "ا",
    "start": 476.988,
    "end": 477.164,
    "idx": 715
  },
  {
    "char": "ل",
    "start": 477.164,
    "end": 477.42,
    "idx": 716
  },
  {
    "char": "شِّ",
    "start": 477.42,
    "end": 477.66,
    "idx": 717
  },
  {
    "char": "مَ",
    "start": 477.66,
    "end": 477.836,
    "idx": 718
  },
  {
    "char": "ا",
    "start": 477.836,
    "end": 477.964,
    "idx": 719
  },
  {
    "char": "لِ",
    "start": 477.964,
    "end": 478.491,
    "idx": 720
  },
  {
    "char": "أَ",
    "start": 485.778,
    "end": 485.93800000000005,
    "idx": 721
  },
  {
    "char": "يَ",
    "start": 485.93800000000005,
    "end": 486.25800000000004,
    "idx": 722
  },
  {
    "char": "طْ",
    "start": 486.25800000000004,
    "end": 486.85,
    "idx": 723
  },
  {
    "char": "مَ",
    "start": 486.85,
    "end": 487.026,
    "idx": 724
  },
  {
    "char": "عُ",
    "start": 487.026,
    "end": 487.502,
    "idx": 725
  },
  {
    "char": "كُ",
    "start": 487.682,
    "end": 488.034,
    "idx": 726
  },
  {
    "char": "لُّ",
    "start": 488.034,
    "end": 488.35400000000004,
    "idx": 727
  },
  {
    "char": "مِّ",
    "start": 488.35400000000004,
    "end": 489.122,
    "idx": 728
  },
  {
    "char": "رِ",
    "start": 489.122,
    "end": 489.37800000000004,
    "idx": 729
  },
  {
    "char": "ئٍ",
    "start": 489.37800000000004,
    "end": 489.686,
    "idx": 730
  },
  {
    "char": "مِّ",
    "start": 490.909,
    "end": 491.101,
    "idx": 731
  },
  {
    "char": "نْ",
    "start": 491.101,
    "end": 491.581,
    "idx": 732
  },
  {
    "char": "هُ",
    "start": 491.581,
    "end": 492.077,
    "idx": 733
  },
  {
    "char": "مْ",
    "start": 492.077,
    "end": 492.452,
    "idx": 734
  },
  {
    "char": "أَ",
    "start": 492.572,
    "end": 492.796,
    "idx": 735
  },
  {
    "char": "نْ",
    "start": 492.796,
    "end": 493.634,
    "idx": 736
  },
  {
    "char": "يُ",
    "start": 493.955,
    "end": 494.131,
    "idx": 737
  },
  {
    "char": "ذْ",
    "start": 494.131,
    "end": 494.387,
    "idx": 738
  },
  {
    "char": "خَ",
    "start": 494.387,
    "end": 494.54699999999997,
    "idx": 739
  },
  {
    "char": "لَ",
    "start": 494.54699999999997,
    "end": 494.877,
    "idx": 740
  },
  {
    "char": "جَ",
    "start": 495.178,
    "end": 496.266,
    "idx": 741
  },
  {
    "char": "نَّ",
    "start": 496.266,
    "end": 496.762,
    "idx": 742
  },
  {
    "char": "ةَ",
    "start": 496.762,
    "end": 497.306,
    "idx": 743
  },
  {
    "char": "نَ",
    "start": 497.306,
    "end": 498.122,
    "idx": 744
  },
  {
    "char": "عِ",
    "start": 498.122,
    "end": 498.57,
    "idx": 745
  },
  {
    "char": "ي",
    "start": 498.57,
    "end": 499.514,
    "idx": 746
  },
  {
    "char": "بٍ",
    "start": 499.514,
    "end": 500.108,
    "idx": 747
  },
  {
    "char": "ك",
    "start": 503.699,
    "end": 504.563,
    "idx": 748
  },
  {
    "char": "ل",
    "start": 504.563,
    "end": 505.235,
    "idx": 749
  },
  {
    "char": "ا",
    "start": 505.235,
    "end": 506.051,
    "idx": 750
  },
  {
    "char": "إ",
    "start": 506.051,
    "end": 507.507,
    "idx": 751
  },
  {
    "char": "ن",
    "start": 507.507,
    "end": 507.779,
    "idx": 752
  },
  {
    "char": "ا",
    "start": 507.779,
    "end": 508.003,
    "idx": 753
  },
  {
    "char": "خ",
    "start": 508.403,
    "end": 508.755,
    "idx": 754
  },
  {
    "char": "ل",
    "start": 508.755,
    "end": 509.283,
    "idx": 755
  },
  {
    "char": "ق",
    "start": 509.283,
    "end": 509.475,
    "idx": 756
  },
  {
    "char": "ن",
    "start": 509.475,
    "end": 509.779,
    "idx": 757
  },
  {
    "char": "ا",
    "start": 509.779,
    "end": 510.00300000000004,
    "idx": 758
  },
  {
    "char": "ه",
    "start": 510.00300000000004,
    "end": 510.61100000000005,
    "idx": 759
  },
  {
    "char": "م",
    "start": 510.61100000000005,
    "end": 511.366,
    "idx": 760
  },
  {
    "char": "م",
    "start": 511.486,
    "end": 512.03,
    "idx": 761
  },
  {
    "char": "م",
    "start": 512.03,
    "end": 512.75,
    "idx": 762
  },
  {
    "char": "ا",
    "start": 512.75,
    "end": 513.054,
    "idx": 763
  },
  {
    "char": "ي",
    "start": 513.054,
    "end": 513.438,
    "idx": 764
  },
  {
    "char": "ع",
    "start": 513.438,
    "end": 513.662,
    "idx": 765
  },
  {
    "char": "ل",
    "start": 513.662,
    "end": 514.478,
    "idx": 766
  },
  {
    "char": "م",
    "start": 514.478,
    "end": 515.694,
    "idx": 767
  },
  {
    "char": "و",
    "start": 515.694,
    "end": 517.278,
    "idx": 768
  },
  {
    "char": "ن",
    "start": 517.278,
    "end": 522.43,
    "idx": 769
  },
  {
    "char": "ف",
    "start": 522.43,
    "end": 522.766,
    "idx": 770
  },
  {
    "char": "ل",
    "start": 522.766,
    "end": 523.262,
    "idx": 771
  },
  {
    "char": "ا",
    "start": 523.262,
    "end": 523.518,
    "idx": 772
  },
  {
    "char": "أ",
    "start": 523.518,
    "end": 524.0459999999999,
    "idx": 773
  },
  {
    "char": "ق",
    "start": 524.0459999999999,
    "end": 524.718,
    "idx": 774
  },
  {
    "char": "س",
    "start": 524.718,
    "end": 525.1179999999999,
    "idx": 775
  },
  {
    "char": "م",
    "start": 525.1179999999999,
    "end": 525.98,
    "idx": 776
  },
  {
    "char": "ب",
    "start": 526.08,
    "end": 526.4960000000001,
    "idx": 777
  },
  {
    "char": "ر",
    "start": 526.4960000000001,
    "end": 527.5680000000001,
    "idx": 778
  },
  {
    "char": "ب",
    "start": 527.5680000000001,
    "end": 528.162,
    "idx": 779
  },
  {
    "char": "ا",
    "start": 528.402,
    "end": 528.514,
    "idx": 780
  },
  {
    "char": "ل",
    "start": 528.514,
    "end": 528.85,
    "idx": 781
  },
  {
    "char": "م",
    "start": 528.85,
    "end": 528.994,
    "idx": 782
  },
  {
    "char": "ش",
    "start": 528.994,
    "end": 529.1220000000001,
    "idx": 783
  },
  {
    "char": "ا",
    "start": 529.1220000000001,
    "end": 529.202,
    "idx": 784
  },
  {
    "char": "ر",
    "start": 529.202,
    "end": 529.298,
    "idx": 785
  },
  {
    "char": "ق",
    "start": 529.298,
    "end": 529.5060000000001,
    "idx": 786
  },
  {
    "char": "و",
    "start": 529.5060000000001,
    "end": 529.5540000000001,
    "idx": 787
  },
  {
    "char": "ن",
    "start": 529.5540000000001,
    "end": 530.044,
    "idx": 788
  },
  {
    "char": "ع",
    "start": 534.023,
    "end": 534.359,
    "idx": 789
  },
  {
    "char": "ل",
    "start": 534.359,
    "end": 534.775,
    "idx": 790
  },
  {
    "char": "ى",
    "start": 534.775,
    "end": 535.045,
    "idx": 791
  },
  {
    "char": "أ",
    "start": 536.106,
    "end": 542.698,
    "idx": 792
  },
  {
    "char": "ن",
    "start": 542.698,
    "end": 543.242,
    "idx": 793
  },
  {
    "char": "ن",
    "start": 543.242,
    "end": 543.93,
    "idx": 794
  },
  {
    "char": "ب",
    "start": 543.93,
    "end": 544.698,
    "idx": 795
  },
  {
    "char": "د",
    "start": 544.698,
    "end": 546.25,
    "idx": 796
  },
  {
    "char": "ل",
    "start": 546.25,
    "end": 547.564,
    "idx": 797
  },
  {
    "char": "خ",
    "start": 547.744,
    "end": 548.048,
    "idx": 798
  },
  {
    "char": "ي",
    "start": 548.048,
    "end": 548.528,
    "idx": 799
  },
  {
    "char": "ر",
    "start": 548.528,
    "end": 548.96,
    "idx": 800
  },
  {
    "char": "ا",
    "start": 548.96,
    "end": 549.567,
    "idx": 801
  },
  {
    "char": "م",
    "start": 549.667,
    "end": 549.779,
    "idx": 802
  },
  {
    "char": "ن",
    "start": 549.779,
    "end": 550.291,
    "idx": 803
  },
  {
    "char": "ه",
    "start": 550.291,
    "end": 550.611,
    "idx": 804
  },
  {
    "char": "م",
    "start": 550.611,
    "end": 551.149,
    "idx": 805
  },
  {
    "char": "و",
    "start": 551.33,
    "end": 551.474,
    "idx": 806
  },
  {
    "char": "م",
    "start": 551.474,
    "end": 551.8100000000001,
    "idx": 807
  },
  {
    "char": "ا",
    "start": 551.8100000000001,
    "end": 552.1940000000001,
    "idx": 808
  },
  {
    "char": "ن",
    "start": 552.1940000000001,
    "end": 552.322,
    "idx": 809
  },
  {
    "char": "ح",
    "start": 552.322,
    "end": 552.7220000000001,
    "idx": 810
  },
  {
    "char": "ن",
    "start": 552.7220000000001,
    "end": 553.573,
    "idx": 811
  },
  {
    "char": "ب",
    "start": 553.673,
    "end": 553.769,
    "idx": 812
  },
  {
    "char": "م",
    "start": 553.769,
    "end": 553.961,
    "idx": 813
  },
  {
    "char": "س",
    "start": 553.961,
    "end": 554.073,
    "idx": 814
  },
  {
    "char": "ب",
    "start": 554.073,
    "end": 554.265,
    "idx": 815
  },
  {
    "char": "و",
    "start": 554.265,
    "end": 554.441,
    "idx": 816
  },
  {
    "char": "ر",
    "start": 554.441,
    "end": 554.935,
    "idx": 817
  },
  {
    "char": "ف",
    "start": 560.483,
    "end": 560.5469999999999,
    "idx": 818
  },
  {
    "char": "ذ",
    "start": 560.5469999999999,
    "end": 560.6909999999999,
    "idx": 819
  },
  {
    "char": "ر",
    "start": 560.6909999999999,
    "end": 560.803,
    "idx": 820
  },
  {
    "char": "ه",
    "start": 560.803,
    "end": 561.3629999999999,
    "idx": 821
  },
  {
    "char": "م",
    "start": 561.3629999999999,
    "end": 561.785,
    "idx": 822
  },
  {
    "char": "ي",
    "start": 561.925,
    "end": 562.021,
    "idx": 823
  },
  {
    "char": "خ",
    "start": 562.021,
    "end": 562.693,
    "idx": 824
  },
  {
    "char": "و",
    "start": 562.693,
    "end": 562.9169999999999,
    "idx": 825
  },
  {
    "char": "ض",
    "start": 562.9169999999999,
    "end": 563.077,
    "idx": 826
  },
  {
    "char": "و",
    "start": 563.077,
    "end": 563.5889999999999,
    "idx": 827
  },
  {
    "char": "ا",
    "start": 563.5889999999999,
    "end": 563.888,
    "idx": 828
  },
  {
    "char": "و",
    "start": 564.248,
    "end": 564.344,
    "idx": 829
  },
  {
    "char": "ي",
    "start": 564.344,
    "end": 564.952,
    "idx": 830
  },
  {
    "char": "ل",
    "start": 564.952,
    "end": 565.432,
    "idx": 831
  },
  {
    "char": "ع",
    "start": 565.432,
    "end": 565.6080000000001,
    "idx": 832
  },
  {
    "char": "ب",
    "start": 565.6080000000001,
    "end": 566.008,
    "idx": 833
  },
  {
    "char": "و",
    "start": 566.008,
    "end": 566.2800000000001,
    "idx": 834
  },
  {
    "char": "ا",
    "start": 566.2800000000001,
    "end": 566.504,
    "idx": 835
  },
  {
    "char": "ح",
    "start": 566.504,
    "end": 567.4960000000001,
    "idx": 836
  },
  {
    "char": "ت",
    "start": 567.4960000000001,
    "end": 567.72,
    "idx": 837
  },
  {
    "char": "ى",
    "start": 567.72,
    "end": 567.9440000000001,
    "idx": 838
  },
  {
    "char": "ي",
    "start": 567.9440000000001,
    "end": 568.6800000000001,
    "idx": 839
  },
  {
    "char": "ل",
    "start": 568.6800000000001,
    "end": 568.808,
    "idx": 840
  },
  {
    "char": "ا",
    "start": 568.808,
    "end": 568.9680000000001,
    "idx": 841
  },
  {
    "char": "ق",
    "start": 568.9680000000001,
    "end": 569.24,
    "idx": 842
  },
  {
    "char": "و",
    "start": 569.24,
    "end": 569.8960000000001,
    "idx": 843
  },
  {
    "char": "ا",
    "start": 569.8960000000001,
    "end": 570.017,
    "idx": 844
  },
  {
    "char": "ي",
    "start": 570.317,
    "end": 570.413,
    "idx": 845
  },
  {
    "char": "و",
    "start": 570.413,
    "end": 571.117,
    "idx": 846
  },
  {
    "char": "م",
    "start": 571.117,
    "end": 571.469,
    "idx": 847
  },
  {
    "char": "ه",
    "start": 571.469,
    "end": 571.677,
    "idx": 848
  },
  {
    "char": "م",
    "start": 571.677,
    "end": 572.173,
    "idx": 849
  },
  {
    "char": "ا",
    "start": 572.173,
    "end": 572.301,
    "idx": 850
  },
  {
    "char": "ل",
    "start": 572.301,
    "end": 572.541,
    "idx": 851
  },
  {
    "char": "ذ",
    "start": 572.541,
    "end": 572.765,
    "idx": 852
  },
  {
    "char": "ي",
    "start": 572.765,
    "end": 573.181,
    "idx": 853
  },
  {
    "char": "ي",
    "start": 573.181,
    "end": 573.389,
    "idx": 854
  },
  {
    "char": "و",
    "start": 573.389,
    "end": 573.485,
    "idx": 855
  },
  {
    "char": "ع",
    "start": 573.485,
    "end": 573.629,
    "idx": 856
  },
  {
    "char": "د",
    "start": 573.629,
    "end": 573.645,
    "idx": 857
  },
  {
    "char": "و",
    "start": 573.645,
    "end": 575.277,
    "idx": 858
  },
  {
    "char": "ن",
    "start": 575.277,
    "end": 577.421,
    "idx": 859
  },
  {
    "char": "ي",
    "start": 577.421,
    "end": 581.373,
    "idx": 860
  },
  {
    "char": "و",
    "start": 581.373,
    "end": 581.741,
    "idx": 861
  },
  {
    "char": "م",
    "start": 581.741,
    "end": 581.934,
    "idx": 862
  },
  {
    "char": "ي",
    "start": 582.014,
    "end": 582.158,
    "idx": 863
  },
  {
    "char": "خ",
    "start": 582.158,
    "end": 582.622,
    "idx": 864
  },
  {
    "char": "ر",
    "start": 582.622,
    "end": 583.086,
    "idx": 865
  },
  {
    "char": "ج",
    "start": 583.086,
    "end": 583.438,
    "idx": 866
  },
  {
    "char": "و",
    "start": 583.438,
    "end": 583.566,
    "idx": 867
  },
  {
    "char": "ن",
    "start": 583.566,
    "end": 583.837,
    "idx": 868
  },
  {
    "char": "م",
    "start": 583.937,
    "end": 584.049,
    "idx": 869
  },
  {
    "char": "ن",
    "start": 584.049,
    "end": 584.577,
    "idx": 870
  },
  {
    "char": "ا",
    "start": 584.577,
    "end": 584.945,
    "idx": 871
  },
  {
    "char": "ل",
    "start": 584.945,
    "end": 585.617,
    "idx": 872
  },
  {
    "char": "أ",
    "start": 585.617,
    "end": 585.809,
    "idx": 873
  },
  {
    "char": "ج",
    "start": 585.809,
    "end": 586.145,
    "idx": 874
  },
  {
    "char": "د",
    "start": 586.145,
    "end": 586.2570000000001,
    "idx": 875
  },
  {
    "char": "ا",
    "start": 586.2570000000001,
    "end": 586.545,
    "idx": 876
  },
  {
    "char": "ف",
    "start": 586.545,
    "end": 586.901,
    "idx": 877
  },
  {
    "char": "س",
    "start": 587.041,
    "end": 587.393,
    "idx": 878
  },
  {
    "char": "ر",
    "start": 587.393,
    "end": 587.745,
    "idx": 879
  },
  {
    "char": "ا",
    "start": 587.745,
    "end": 588.129,
    "idx": 880
  },
  {
    "char": "ع",
    "start": 588.129,
    "end": 588.3850000000001,
    "idx": 881
  },
  {
    "char": "ا",
    "start": 588.3850000000001,
    "end": 588.904,
    "idx": 882
  },
  {
    "char": "ك",
    "start": 589.508,
    "end": 589.716,
    "idx": 883
  },
  {
    "char": "أ",
    "start": 589.716,
    "end": 589.86,
    "idx": 884
  },
  {
    "char": "ن",
    "start": 589.86,
    "end": 591.428,
    "idx": 885
  },
  {
    "char": "ه",
    "start": 591.428,
    "end": 591.716,
    "idx": 886
  },
  {
    "char": "م",
    "start": 591.716,
    "end": 592.193,
    "idx": 887
  },
  {
    "char": "إ",
    "start": 592.273,
    "end": 592.625,
    "idx": 888
  },
  {
    "char": "ل",
    "start": 592.625,
    "end": 592.849,
    "idx": 889
  },
  {
    "char": "ى",
    "start": 592.849,
    "end": 593.1850000000001,
    "idx": 890
  },
  {
    "char": "ن",
    "start": 593.1850000000001,
    "end": 593.681,
    "idx": 891
  },
  {
    "char": "ص",
    "start": 593.681,
    "end": 594.2570000000001,
    "idx": 892
  },
  {
    "char": "ب",
    "start": 594.2570000000001,
    "end": 594.721,
    "idx": 893
  },
  {
    "char": "ي",
    "start": 594.721,
    "end": 595.025,
    "idx": 894
  },
  {
    "char": "ن",
    "start": 595.025,
    "end": 595.553,
    "idx": 895
  },
  {
    "char": "ف",
    "start": 595.553,
    "end": 596.2090000000001,
    "idx": 896
  },
  {
    "char": "ض",
    "start": 596.2090000000001,
    "end": 596.5450000000001,
    "idx": 897
  },
  {
    "char": "و",
    "start": 596.5450000000001,
    "end": 599.7610000000001,
    "idx": 898
  },
  {
    "char": "ن",
    "start": 599.7610000000001,
    "end": 601.921,
    "idx": 899
  },
  {
    "char": "خ",
    "start": 601.921,
    "end": 602.177,
    "idx": 900
  },
  {
    "char": "ا",
    "start": 602.177,
    "end": 602.385,
    "idx": 901
  },
  {
    "char": "ش",
    "start": 602.385,
    "end": 602.801,
    "idx": 902
  },
  {
    "char": "ع",
    "start": 602.801,
    "end": 603.169,
    "idx": 903
  },
  {
    "char": "ة",
    "start": 603.169,
    "end": 603.532,
    "idx": 904
  },
  {
    "char": "أ",
    "start": 604.153,
    "end": 604.249,
    "idx": 905
  },
  {
    "char": "ب",
    "start": 604.249,
    "end": 604.4730000000001,
    "idx": 906
  },
  {
    "char": "ص",
    "start": 604.4730000000001,
    "end": 604.777,
    "idx": 907
  },
  {
    "char": "ا",
    "start": 604.777,
    "end": 605.385,
    "idx": 908
  },
  {
    "char": "ر",
    "start": 605.385,
    "end": 605.977,
    "idx": 909
  },
  {
    "char": "ه",
    "start": 605.977,
    "end": 606.3290000000001,
    "idx": 910
  },
  {
    "char": "م",
    "start": 606.3290000000001,
    "end": 606.937,
    "idx": 911
  },
  {
    "char": "ت",
    "start": 606.937,
    "end": 607.225,
    "idx": 912
  },
  {
    "char": "ر",
    "start": 607.225,
    "end": 607.689,
    "idx": 913
  },
  {
    "char": "ه",
    "start": 607.689,
    "end": 608.009,
    "idx": 914
  },
  {
    "char": "ق",
    "start": 608.009,
    "end": 608.2330000000001,
    "idx": 915
  },
  {
    "char": "ه",
    "start": 608.2330000000001,
    "end": 609.065,
    "idx": 916
  },
  {
    "char": "م",
    "start": 609.065,
    "end": 609.402,
    "idx": 917
  },
  {
    "char": "ذ",
    "start": 609.522,
    "end": 609.634,
    "idx": 918
  },
  {
    "char": "ل",
    "start": 609.634,
    "end": 610.5780000000001,
    "idx": 919
  },
  {
    "char": "ة",
    "start": 610.5780000000001,
    "end": 611.145,
    "idx": 920
  },
  {
    "char": "ذ",
    "start": 613.336,
    "end": 613.7040000000001,
    "idx": 921
  },
  {
    "char": "ل",
    "start": 613.7040000000001,
    "end": 613.944,
    "idx": 922
  },
  {
    "char": "ك",
    "start": 613.944,
    "end": 614.024,
    "idx": 923
  },
  {
    "char": "ا",
    "start": 614.024,
    "end": 614.136,
    "idx": 924
  },
  {
    "char": "ل",
    "start": 614.136,
    "end": 614.28,
    "idx": 925
  },
  {
    "char": "ي",
    "start": 614.28,
    "end": 614.792,
    "idx": 926
  },
  {
    "char": "و",
    "start": 614.792,
    "end": 615.48,
    "idx": 927
  },
  {
    "char": "م",
    "start": 615.48,
    "end": 616.696,
    "idx": 928
  },
  {
    "char": "ا",
    "start": 616.696,
    "end": 617.16,
    "idx": 929
  },
  {
    "char": "ل",
    "start": 617.16,
    "end": 617.448,
    "idx": 930
  },
  {
    "char": "ذ",
    "start": 617.448,
    "end": 617.7520000000001,
    "idx": 931
  },
  {
    "char": "ي",
    "start": 617.7520000000001,
    "end": 618.154,
    "idx": 932
  },
  {
    "char": "ك",
    "start": 618.395,
    "end": 618.747,
    "idx": 933
  },
  {
    "char": "ا",
    "start": 618.747,
    "end": 618.971,
    "idx": 934
  },
  {
    "char": "ن",
    "start": 618.971,
    "end": 619.483,
    "idx": 935
  },
  {
    "char": "و",
    "start": 619.483,
    "end": 620.091,
    "idx": 936
  },
  {
    "char": "ا",
    "start": 620.091,
    "end": 620.523,
    "idx": 937
  },
  {
    "char": "ي",
    "start": 620.523,
    "end": 620.939,
    "idx": 938
  },
  {
    "char": "و",
    "start": 620.939,
    "end": 621.307,
    "idx": 939
  },
  {
    "char": "ع",
    "start": 621.307,
    "end": 621.947,
    "idx": 940
  },
  {
    "char": "د",
    "start": 621.947,
    "end": 622.507,
    "idx": 941
  },
  {
    "char": "و",
    "start": 622.507,
    "end": 622.795,
    "idx": 942
  },
  {
    "char": "ن",
    "start": 622.795,
    "end": 623.734,
    "idx": 943
  }
]